{
    "home": {
        "overview": {
            "acqdate": "2020-04-22  09:20:06",
            "CVTgraph_pn": {
                "infected": {
                    "day": 366,
                    "week": 2624
                },
                "tweet": {
                    "day": 9034,
                    "week": 61001
                }
            }
        }
    },
    "words": {
        "words": {
            "words_pn": {
                "count": 473992,
                "count_unk": 23241
            }
        },
        "posi-nega": {
            "type": "doughnut",
            "data": {
                "labels": [
                    "positive",
                    "neutral",
                    "negative"
                ],
                "datasets": [
                    {
                        "label": "",
                        "data": [
                            10470,
                            15765,
                            25752
                        ],
                        "backgroundColor": [
                            "#FB7B8E",
                            "#FDC094",
                            "#6096FD"
                        ]
                    }
                ]
            },
            "options": {
                "legend": {
                    "display": false
                },
                "title": {
                    "display": false
                },
                "tooltips": {
                    "callbacks": {
                        "label": []
                    }
                }
            }
        },
        "count": [
            {
                "原形": "コロナ",
                "品詞": "名詞",
                "品詞細分類": "普通名詞",
                "出現回数": 7990
            },
            {
                "原形": "新型",
                "品詞": "名詞",
                "品詞細分類": "普通名詞",
                "出現回数": 4091
            },
            {
                "原形": "感染",
                "品詞": "名詞",
                "品詞細分類": "サ変名詞",
                "出現回数": 3529
            },
            {
                "原形": "コロナウイルス",
                "品詞": "未定義語",
                "品詞細分類": "カタカナ",
                "出現回数": 1570
            },
            {
                "原形": "人",
                "品詞": "名詞",
                "品詞細分類": "普通名詞",
                "出現回数": 1520
            },
            {
                "原形": "ウイルス",
                "品詞": "名詞",
                "品詞細分類": "普通名詞",
                "出現回数": 1284
            },
            {
                "原形": "日本",
                "品詞": "名詞",
                "品詞細分類": "地名",
                "出現回数": 1145
            },
            {
                "原形": "拡大",
                "品詞": "名詞",
                "品詞細分類": "サ変名詞",
                "出現回数": 958
            },
            {
                "原形": "思う",
                "品詞": "動詞",
                "品詞細分類": "*",
                "出現回数": 913
            },
            {
                "原形": "対策",
                "品詞": "名詞",
                "品詞細分類": "普通名詞",
                "出現回数": 873
            },
            {
                "原形": "検査",
                "品詞": "名詞",
                "品詞細分類": "サ変名詞",
                "出現回数": 786
            },
            {
                "原形": "できる",
                "品詞": "動詞",
                "品詞細分類": "*",
                "出現回数": 751
            },
            {
                "原形": "影響",
                "品詞": "名詞",
                "品詞細分類": "サ変名詞",
                "出現回数": 731
            },
            {
                "原形": "ない",
                "品詞": "形容詞",
                "品詞細分類": "*",
                "出現回数": 693
            },
            {
                "原形": "言う",
                "品詞": "動詞",
                "品詞細分類": "*",
                "出現回数": 641
            },
            {
                "原形": "今",
                "品詞": "名詞",
                "品詞細分類": "時相名詞",
                "出現回数": 638
            },
            {
                "原形": "症",
                "品詞": "名詞",
                "品詞細分類": "普通名詞",
                "出現回数": 624
            },
            {
                "原形": "医療",
                "品詞": "名詞",
                "品詞細分類": "普通名詞",
                "出現回数": 594
            },
            {
                "原形": "願う",
                "品詞": "動詞",
                "品詞細分類": "*",
                "出現回数": 578
            },
            {
                "原形": "つく",
                "品詞": "動詞",
                "品詞細分類": "*",
                "出現回数": 560
            },
            {
                "原形": "自粛",
                "品詞": "名詞",
                "品詞細分類": "サ変名詞",
                "出現回数": 556
            },
            {
                "原形": "事",
                "品詞": "名詞",
                "品詞細分類": "普通名詞",
                "出現回数": 539
            },
            {
                "原形": "確認",
                "品詞": "名詞",
                "品詞細分類": "サ変名詞",
                "出現回数": 476
            },
            {
                "原形": "国",
                "品詞": "名詞",
                "品詞細分類": "普通名詞",
                "出現回数": 461
            },
            {
                "原形": "店",
                "品詞": "名詞",
                "品詞細分類": "普通名詞",
                "出現回数": 449
            },
            {
                "原形": "私",
                "品詞": "名詞",
                "品詞細分類": "普通名詞",
                "出現回数": 439
            },
            {
                "原形": "世界",
                "品詞": "名詞",
                "品詞細分類": "普通名詞",
                "出現回数": 437
            },
            {
                "原形": "緊急だ",
                "品詞": "形容詞",
                "品詞細分類": "*",
                "出現回数": 435
            },
            {
                "原形": "出る",
                "品詞": "動詞",
                "品詞細分類": "*",
                "出現回数": 431
            },
            {
                "原形": "中国",
                "品詞": "名詞",
                "品詞細分類": "地名",
                "出現回数": 421
            },
            {
                "原形": "防止",
                "品詞": "名詞",
                "品詞細分類": "サ変名詞",
                "出現回数": 418
            },
            {
                "原形": "マスク",
                "品詞": "名詞",
                "品詞細分類": "普通名詞",
                "出現回数": 408
            },
            {
                "原形": "休業",
                "品詞": "名詞",
                "品詞細分類": "サ変名詞",
                "出現回数": 396
            },
            {
                "原形": "見る",
                "品詞": "動詞",
                "品詞細分類": "*",
                "出現回数": 396
            },
            {
                "原形": "情報",
                "品詞": "名詞",
                "品詞細分類": "普通名詞",
                "出現回数": 392
            },
            {
                "原形": "やる",
                "品詞": "動詞",
                "品詞細分類": "*",
                "出現回数": 391
            },
            {
                "原形": "対応",
                "品詞": "名詞",
                "品詞細分類": "サ変名詞",
                "出現回数": 387
            },
            {
                "原形": "受ける",
                "品詞": "動詞",
                "品詞細分類": "*",
                "出現回数": 382
            },
            {
                "原形": "事態",
                "品詞": "名詞",
                "品詞細分類": "普通名詞",
                "出現回数": 381
            },
            {
                "原形": "支援",
                "品詞": "名詞",
                "品詞細分類": "サ変名詞",
                "出現回数": 378
            },
            {
                "原形": "政府",
                "品詞": "名詞",
                "品詞細分類": "普通名詞",
                "出現回数": 377
            },
            {
                "原形": "いい",
                "品詞": "形容詞",
                "品詞細分類": "*",
                "出現回数": 352
            },
            {
                "原形": "状況",
                "品詞": "名詞",
                "品詞細分類": "普通名詞",
                "出現回数": 348
            },
            {
                "原形": "経済",
                "品詞": "名詞",
                "品詞細分類": "普通名詞",
                "出現回数": 343
            },
            {
                "原形": "今日",
                "品詞": "名詞",
                "品詞細分類": "時相名詞",
                "出現回数": 338
            },
            {
                "原形": "病院",
                "品詞": "名詞",
                "品詞細分類": "普通名詞",
                "出現回数": 333
            },
            {
                "原形": "金",
                "品詞": "名詞",
                "品詞細分類": "普通名詞",
                "出現回数": 331
            },
            {
                "原形": "患者",
                "品詞": "名詞",
                "品詞細分類": "普通名詞",
                "出現回数": 320
            },
            {
                "原形": "ニュース",
                "品詞": "名詞",
                "品詞細分類": "普通名詞",
                "出現回数": 317
            },
            {
                "原形": "営業",
                "品詞": "名詞",
                "品詞細分類": "サ変名詞",
                "出現回数": 311
            },
            {
                "原形": "自分",
                "品詞": "名詞",
                "品詞細分類": "普通名詞",
                "出現回数": 308
            },
            {
                "原形": "所",
                "品詞": "名詞",
                "品詞細分類": "普通名詞",
                "出現回数": 305
            },
            {
                "原形": "東京",
                "品詞": "名詞",
                "品詞細分類": "地名",
                "出現回数": 304
            },
            {
                "原形": "気",
                "品詞": "名詞",
                "品詞細分類": "普通名詞",
                "出現回数": 300
            },
            {
                "原形": "死亡",
                "品詞": "名詞",
                "品詞細分類": "サ変名詞",
                "出現回数": 298
            },
            {
                "原形": "コロナウィルス",
                "品詞": "未定義語",
                "品詞細分類": "カタカナ",
                "出現回数": 297
            },
            {
                "原形": "日",
                "品詞": "名詞",
                "品詞細分類": "地名",
                "出現回数": 297
            },
            {
                "原形": "方",
                "品詞": "名詞",
                "品詞細分類": "普通名詞",
                "出現回数": 296
            },
            {
                "原形": "くださる",
                "品詞": "動詞",
                "品詞細分類": "*",
                "出現回数": 293
            },
            {
                "原形": "いただく",
                "品詞": "動詞",
                "品詞細分類": "*",
                "出現回数": 289
            },
            {
                "原形": "国民",
                "品詞": "名詞",
                "品詞細分類": "普通名詞",
                "出現回数": 287
            },
            {
                "原形": "考える",
                "品詞": "動詞",
                "品詞細分類": "*",
                "出現回数": 284
            },
            {
                "原形": "時間",
                "品詞": "名詞",
                "品詞細分類": "時相名詞",
                "出現回数": 283
            },
            {
                "原形": "いたす",
                "品詞": "動詞",
                "品詞細分類": "*",
                "出現回数": 278
            },
            {
                "原形": "延期",
                "品詞": "名詞",
                "品詞細分類": "サ変名詞",
                "出現回数": 275
            },
            {
                "原形": "必要だ",
                "品詞": "形容詞",
                "品詞細分類": "*",
                "出現回数": 273
            },
            {
                "原形": "皆様",
                "品詞": "名詞",
                "品詞細分類": "普通名詞",
                "出現回数": 272
            },
            {
                "原形": "宣言",
                "品詞": "名詞",
                "品詞細分類": "サ変名詞",
                "出現回数": 272
            },
            {
                "原形": "発表",
                "品詞": "名詞",
                "品詞細分類": "サ変名詞",
                "出現回数": 271
            },
            {
                "原形": "行く",
                "品詞": "動詞",
                "品詞細分類": "*",
                "出現回数": 269
            },
            {
                "原形": "外出",
                "品詞": "名詞",
                "品詞細分類": "サ変名詞",
                "出現回数": 266
            },
            {
                "原形": "生活",
                "品詞": "名詞",
                "品詞細分類": "サ変名詞",
                "出現回数": 261
            },
            {
                "原形": "判明",
                "品詞": "名詞",
                "品詞細分類": "サ変名詞",
                "出現回数": 259
            },
            {
                "原形": "中止",
                "品詞": "名詞",
                "品詞細分類": "サ変名詞",
                "出現回数": 257
            },
            {
                "原形": "多い",
                "品詞": "形容詞",
                "品詞細分類": "*",
                "出現回数": 256
            },
            {
                "原形": "放送",
                "品詞": "名詞",
                "品詞細分類": "サ変名詞",
                "出現回数": 254
            },
            {
                "原形": "会",
                "品詞": "名詞",
                "品詞細分類": "普通名詞",
                "出現回数": 250
            },
            {
                "原形": "関係",
                "品詞": "名詞",
                "品詞細分類": "サ変名詞",
                "出現回数": 250
            },
            {
                "原形": "出来る",
                "品詞": "動詞",
                "品詞細分類": "*",
                "出現回数": 247
            },
            {
                "原形": "問題",
                "品詞": "名詞",
                "品詞細分類": "普通名詞",
                "出現回数": 246
            },
            {
                "原形": "変死",
                "品詞": "名詞",
                "品詞細分類": "サ変名詞",
                "出現回数": 246
            },
            {
                "原形": "頑張る",
                "品詞": "動詞",
                "品詞細分類": "*",
                "出現回数": 243
            },
            {
                "原形": "早い",
                "品詞": "形容詞",
                "品詞細分類": "*",
                "出現回数": 242
            },
            {
                "原形": "開催",
                "品詞": "名詞",
                "品詞細分類": "サ変名詞",
                "出現回数": 241
            },
            {
                "原形": "話",
                "品詞": "名詞",
                "品詞細分類": "サ変名詞",
                "出現回数": 241
            },
            {
                "原形": "行う",
                "品詞": "動詞",
                "品詞細分類": "*",
                "出現回数": 241
            },
            {
                "原形": "予定",
                "品詞": "名詞",
                "品詞細分類": "サ変名詞",
                "出現回数": 240
            },
            {
                "原形": "本当だ",
                "品詞": "形容詞",
                "品詞細分類": "*",
                "出現回数": 237
            },
            {
                "原形": "県",
                "品詞": "名詞",
                "品詞細分類": "普通名詞",
                "出現回数": 237
            },
            {
                "原形": "新ただ",
                "品詞": "形容詞",
                "品詞細分類": "*",
                "出現回数": 237
            },
            {
                "原形": "自宅",
                "品詞": "名詞",
                "品詞細分類": "普通名詞",
                "出現回数": 235
            },
            {
                "原形": "危機",
                "品詞": "名詞",
                "品詞細分類": "普通名詞",
                "出現回数": 234
            },
            {
                "原形": "死者",
                "品詞": "名詞",
                "品詞細分類": "普通名詞",
                "出現回数": 233
            },
            {
                "原形": "臨時",
                "品詞": "名詞",
                "品詞細分類": "普通名詞",
                "出現回数": 232
            },
            {
                "原形": "可能だ",
                "品詞": "形容詞",
                "品詞細分類": "*",
                "出現回数": 228
            },
            {
                "原形": "知らせ",
                "品詞": "名詞",
                "品詞細分類": "普通名詞",
                "出現回数": 226
            },
            {
                "原形": "負ける",
                "品詞": "動詞",
                "品詞細分類": "*",
                "出現回数": 225
            },
            {
                "原形": "良い",
                "品詞": "形容詞",
                "品詞細分類": "*",
                "出現回数": 224
            },
            {
                "原形": "協力",
                "品詞": "名詞",
                "品詞細分類": "サ変名詞",
                "出現回数": 224
            },
            {
                "原形": "米",
                "品詞": "名詞",
                "品詞細分類": "地名",
                "出現回数": 223
            }
        ],
        "w2v": {
            "type": "bubble",
            "data": {
                "datasets": [
                    {
                        "label": "動詞",
                        "backgroundColor": "#6096FD",
                        "data": [
                            {
                                "x": -1.7872776985168457,
                                "y": -1.826738953590393,
                                "r": 3.621861722672847,
                                "c": 913
                            },
                            {
                                "x": -0.7719247937202454,
                                "y": -0.7115887403488159,
                                "r": 3.4758594051757434,
                                "c": 751
                            },
                            {
                                "x": -2.110185384750366,
                                "y": -1.2369135618209839,
                                "r": 3.3767220290974636,
                                "c": 641
                            },
                            {
                                "x": 2.3981900215148926,
                                "y": -2.5434157848358154,
                                "r": 3.3199433500708126,
                                "c": 578
                            },
                            {
                                "x": 0.8882607221603394,
                                "y": 0.6053311824798584,
                                "r": 3.3037208703489123,
                                "c": 560
                            },
                            {
                                "x": -1.2231144905090332,
                                "y": -0.17080722749233246,
                                "r": 3.187459765675293,
                                "c": 431
                            },
                            {
                                "x": -1.385733962059021,
                                "y": -1.309795618057251,
                                "r": 3.1559160551049312,
                                "c": 396
                            },
                            {
                                "x": -1.2794556617736816,
                                "y": -1.4743971824645996,
                                "r": 3.1514098107377366,
                                "c": 391
                            },
                            {
                                "x": 0.995917558670044,
                                "y": 0.6210218667984009,
                                "r": 3.1432985708767864,
                                "c": 382
                            },
                            {
                                "x": 1.7709256410598755,
                                "y": -0.6787895560264587,
                                "r": 3.0630874211407235,
                                "c": 293
                            },
                            {
                                "x": 2.746903657913208,
                                "y": -1.132080078125,
                                "r": 3.059482425646968,
                                "c": 289
                            },
                            {
                                "x": -1.2148994207382202,
                                "y": -1.188191533088684,
                                "r": 3.0549761812797733,
                                "c": 284
                            },
                            {
                                "x": 3.3644003868103027,
                                "y": -1.0405501127243042,
                                "r": 3.04956868803914,
                                "c": 278
                            },
                            {
                                "x": -1.0092545747756958,
                                "y": -1.8537260293960571,
                                "r": 3.04145744817819,
                                "c": 269
                            },
                            {
                                "x": -0.5755013823509216,
                                "y": -1.7246698141098022,
                                "r": 3.021629972962534,
                                "c": 247
                            },
                            {
                                "x": -0.21004830300807953,
                                "y": -2.602670431137085,
                                "r": 3.018024977468778,
                                "c": 243
                            },
                            {
                                "x": 0.5159249305725098,
                                "y": -0.07667409628629684,
                                "r": 3.0162224797219004,
                                "c": 241
                            },
                            {
                                "x": 0.025224849581718445,
                                "y": -2.208395481109619,
                                "r": 3.001802497746878,
                                "c": 225
                            }
                        ]
                    },
                    {
                        "label": "未定義語",
                        "backgroundColor": "#FDC094",
                        "data": [
                            {
                                "x": 1.3268113136291504,
                                "y": 2.746656656265259,
                                "r": 4.213982232522209,
                                "c": 1570
                            },
                            {
                                "x": 0.6815938949584961,
                                "y": 0.9154174327850342,
                                "r": 3.066692416634479,
                                "c": 297
                            }
                        ]
                    },
                    {
                        "label": "名詞",
                        "backgroundColor": "#FF9190",
                        "data": [
                            {
                                "x": -0.8945909738540649,
                                "y": -0.15506668388843536,
                                "r": 10.0,
                                "c": 7990
                            },
                            {
                                "x": 0.516294002532959,
                                "y": 2.410120964050293,
                                "r": 6.486030642461698,
                                "c": 4091
                            },
                            {
                                "x": 0.29195636510849,
                                "y": 2.7923030853271484,
                                "r": 5.9795287755890305,
                                "c": 3529
                            },
                            {
                                "x": -2.6919941902160645,
                                "y": -0.7890531420707703,
                                "r": 4.168919788850264,
                                "c": 1520
                            },
                            {
                                "x": 0.3304353952407837,
                                "y": 1.052945613861084,
                                "r": 3.9562250547186815,
                                "c": 1284
                            },
                            {
                                "x": -2.099893808364868,
                                "y": 0.1769072413444519,
                                "r": 3.8309514613106734,
                                "c": 1145
                            },
                            {
                                "x": 2.568305730819702,
                                "y": 2.1294426918029785,
                                "r": 3.6624179219775974,
                                "c": 958
                            },
                            {
                                "x": 0.37841230630874634,
                                "y": -0.05456820875406265,
                                "r": 3.58581176773529,
                                "c": 873
                            },
                            {
                                "x": -2.94685697555542,
                                "y": 2.0672788619995117,
                                "r": 3.507403115746105,
                                "c": 786
                            },
                            {
                                "x": 1.343883991241455,
                                "y": -0.18923047184944153,
                                "r": 3.4578344277069655,
                                "c": 731
                            },
                            {
                                "x": -1.4067093133926392,
                                "y": -1.8502124547958374,
                                "r": 3.374018282477147,
                                "c": 638
                            },
                            {
                                "x": 1.3589155673980713,
                                "y": 2.4514875411987305,
                                "r": 3.361400798249002,
                                "c": 624
                            },
                            {
                                "x": -2.291050434112549,
                                "y": 0.3428008556365967,
                                "r": 3.334363332045835,
                                "c": 594
                            },
                            {
                                "x": 0.7055699825286865,
                                "y": -1.4613653421401978,
                                "r": 3.3001158748551562,
                                "c": 556
                            },
                            {
                                "x": -1.3442552089691162,
                                "y": -1.795561671257019,
                                "r": 3.284794644006695,
                                "c": 539
                            },
                            {
                                "x": -0.08096665889024734,
                                "y": 3.0181779861450195,
                                "r": 3.228015964980044,
                                "c": 476
                            },
                            {
                                "x": -1.4127039909362793,
                                "y": 0.25975874066352844,
                                "r": 3.21449723187846,
                                "c": 461
                            },
                            {
                                "x": 1.6673204898834229,
                                "y": -1.5801277160644531,
                                "r": 3.2036822453971934,
                                "c": 449
                            },
                            {
                                "x": -1.2848200798034668,
                                "y": -1.562992811203003,
                                "r": 3.194669756662804,
                                "c": 439
                            },
                            {
                                "x": -1.4972060918807983,
                                "y": -0.40158647298812866,
                                "r": 3.1928672589159266,
                                "c": 437
                            },
                            {
                                "x": -1.7996487617492676,
                                "y": 0.8030843734741211,
                                "r": 3.178447276940904,
                                "c": 421
                            },
                            {
                                "x": 3.3547873497009277,
                                "y": 1.7538248300552368,
                                "r": 3.175743530320587,
                                "c": 418
                            },
                            {
                                "x": -0.8001903295516968,
                                "y": -0.8753461837768555,
                                "r": 3.166731041586198,
                                "c": 408
                            },
                            {
                                "x": 3.330690383911133,
                                "y": -0.37882912158966064,
                                "r": 3.1559160551049312,
                                "c": 396
                            },
                            {
                                "x": 0.44707024097442627,
                                "y": 0.9726048707962036,
                                "r": 3.1523110596111756,
                                "c": 392
                            },
                            {
                                "x": -0.20688720047473907,
                                "y": 0.3283330798149109,
                                "r": 3.147804815243981,
                                "c": 387
                            },
                            {
                                "x": 2.3350367546081543,
                                "y": 0.6855709552764893,
                                "r": 3.1423973220033474,
                                "c": 381
                            },
                            {
                                "x": 0.8074954748153687,
                                "y": -0.4310923218727112,
                                "r": 3.139693575383031,
                                "c": 378
                            },
                            {
                                "x": -0.8012229800224304,
                                "y": 0.0904121994972229,
                                "r": 3.138792326509592,
                                "c": 377
                            },
                            {
                                "x": 0.4979948103427887,
                                "y": 0.07373840361833572,
                                "r": 3.1126561091798637,
                                "c": 348
                            },
                            {
                                "x": -0.7527503967285156,
                                "y": -0.10202999413013458,
                                "r": 3.108149864812669,
                                "c": 343
                            },
                            {
                                "x": -0.19660431146621704,
                                "y": -1.6786240339279175,
                                "r": 3.1036436204454745,
                                "c": 338
                            },
                            {
                                "x": -2.2298340797424316,
                                "y": 1.3272379636764526,
                                "r": 3.09913737607828,
                                "c": 333
                            },
                            {
                                "x": 0.21471138298511505,
                                "y": -0.7610170841217041,
                                "r": 3.0973348783314023,
                                "c": 331
                            },
                            {
                                "x": -1.6909401416778564,
                                "y": 2.028982162475586,
                                "r": 3.087421140723574,
                                "c": 320
                            },
                            {
                                "x": -1.0102084875106812,
                                "y": 0.7369852066040039,
                                "r": 3.0847173941032575,
                                "c": 317
                            },
                            {
                                "x": 3.3740532398223877,
                                "y": -0.9631955623626709,
                                "r": 3.079309900862624,
                                "c": 311
                            },
                            {
                                "x": -1.844326376914978,
                                "y": -1.8423948287963867,
                                "r": 3.0766061542423073,
                                "c": 308
                            },
                            {
                                "x": -1.1747610569000244,
                                "y": 1.2912756204605103,
                                "r": 3.0739024076219903,
                                "c": 305
                            },
                            {
                                "x": -0.5980412364006042,
                                "y": 1.2096707820892334,
                                "r": 3.0730011587485517,
                                "c": 304
                            },
                            {
                                "x": -0.9498399496078491,
                                "y": -1.929004192352295,
                                "r": 3.069396163254796,
                                "c": 300
                            },
                            {
                                "x": -2.648709774017334,
                                "y": 2.9439120292663574,
                                "r": 3.067593665507918,
                                "c": 298
                            },
                            {
                                "x": 1.4308041334152222,
                                "y": -1.0966911315917969,
                                "r": 3.066692416634479,
                                "c": 297
                            },
                            {
                                "x": -0.08264647424221039,
                                "y": -0.7838542461395264,
                                "r": 3.06579116776104,
                                "c": 296
                            },
                            {
                                "x": -1.2654459476470947,
                                "y": -0.6160489320755005,
                                "r": 3.05767992790009,
                                "c": 287
                            },
                            {
                                "x": 1.255056381225586,
                                "y": -0.9867535829544067,
                                "r": 3.0540749324063343,
                                "c": 283
                            },
                            {
                                "x": 2.6870574951171875,
                                "y": 0.2156810760498047,
                                "r": 3.046864941418823,
                                "c": 275
                            },
                            {
                                "x": 1.765420913696289,
                                "y": -1.7009525299072266,
                                "r": 3.0441611947985066,
                                "c": 272
                            },
                            {
                                "x": 2.8821728229522705,
                                "y": 0.872700572013855,
                                "r": 3.0441611947985066,
                                "c": 272
                            },
                            {
                                "x": 0.6236628890037537,
                                "y": 1.6388756036758423,
                                "r": 3.0432599459250675,
                                "c": 271
                            },
                            {
                                "x": 0.6060376167297363,
                                "y": -0.904676079750061,
                                "r": 3.038753701557873,
                                "c": 266
                            },
                            {
                                "x": -0.5186439752578735,
                                "y": -0.6505018472671509,
                                "r": 3.0342474571906783,
                                "c": 261
                            },
                            {
                                "x": -2.4515509605407715,
                                "y": 3.7888565063476562,
                                "r": 3.0324449594438008,
                                "c": 259
                            },
                            {
                                "x": 2.4377622604370117,
                                "y": 0.05970100313425064,
                                "r": 3.0306424616969228,
                                "c": 257
                            },
                            {
                                "x": 1.892587423324585,
                                "y": 0.00010577961802482605,
                                "r": 3.027938715076606,
                                "c": 254
                            },
                            {
                                "x": 0.6502341032028198,
                                "y": 0.3350212574005127,
                                "r": 3.0243337195828506,
                                "c": 250
                            },
                            {
                                "x": -1.311856985092163,
                                "y": -0.1252387911081314,
                                "r": 3.0243337195828506,
                                "c": 250
                            },
                            {
                                "x": -1.348399043083191,
                                "y": -0.3243325352668762,
                                "r": 3.020728724089095,
                                "c": 246
                            },
                            {
                                "x": -3.094536066055298,
                                "y": 3.443039894104004,
                                "r": 3.020728724089095,
                                "c": 246
                            },
                            {
                                "x": 2.951808214187622,
                                "y": 0.25016188621520996,
                                "r": 3.0162224797219004,
                                "c": 241
                            },
                            {
                                "x": -0.6650323271751404,
                                "y": -0.6904430389404297,
                                "r": 3.0162224797219004,
                                "c": 241
                            },
                            {
                                "x": 2.904327392578125,
                                "y": 0.2313031703233719,
                                "r": 3.0153212308484614,
                                "c": 240
                            },
                            {
                                "x": 0.4965822994709015,
                                "y": 2.3079001903533936,
                                "r": 3.012617484228145,
                                "c": 237
                            },
                            {
                                "x": -1.3219153881072998,
                                "y": 0.8416966795921326,
                                "r": 3.0108149864812668,
                                "c": 235
                            },
                            {
                                "x": -1.0030417442321777,
                                "y": -0.08566790819168091,
                                "r": 3.009913737607828,
                                "c": 234
                            },
                            {
                                "x": -2.2008094787597656,
                                "y": 1.5059309005737305,
                                "r": 3.009012488734389,
                                "c": 233
                            },
                            {
                                "x": 3.8566277027130127,
                                "y": 0.8098506927490234,
                                "r": 3.00811123986095,
                                "c": 232
                            },
                            {
                                "x": 3.4946508407592773,
                                "y": 1.4436719417572021,
                                "r": 3.0027037466203166,
                                "c": 226
                            },
                            {
                                "x": 2.2968900203704834,
                                "y": -1.5703623294830322,
                                "r": 3.000901248873439,
                                "c": 224
                            },
                            {
                                "x": -0.9886555671691895,
                                "y": 0.5323050618171692,
                                "r": 3.0,
                                "c": 223
                            }
                        ]
                    },
                    {
                        "label": "形容詞",
                        "backgroundColor": "#031B88",
                        "data": [
                            {
                                "x": -1.810176134109497,
                                "y": -1.0184860229492188,
                                "r": 3.4235869705162867,
                                "c": 693
                            },
                            {
                                "x": 2.259640693664551,
                                "y": 0.8159095048904419,
                                "r": 3.1910647611690486,
                                "c": 435
                            },
                            {
                                "x": -1.965796709060669,
                                "y": -1.6150126457214355,
                                "r": 3.1162611046736193,
                                "c": 352
                            },
                            {
                                "x": -0.7030341625213623,
                                "y": -0.47408777475357056,
                                "r": 3.0450624436719456,
                                "c": 273
                            },
                            {
                                "x": -1.8994343280792236,
                                "y": -0.1663430631160736,
                                "r": 3.029741212823484,
                                "c": 256
                            },
                            {
                                "x": -0.38690078258514404,
                                "y": -1.690265417098999,
                                "r": 3.0171237285953394,
                                "c": 242
                            },
                            {
                                "x": -1.3343843221664429,
                                "y": -1.408418893814087,
                                "r": 3.012617484228145,
                                "c": 237
                            },
                            {
                                "x": -0.31852465867996216,
                                "y": 2.7910232543945312,
                                "r": 3.012617484228145,
                                "c": 237
                            },
                            {
                                "x": -0.5065042972564697,
                                "y": 0.152252197265625,
                                "r": 3.0045062443671946,
                                "c": 228
                            },
                            {
                                "x": -1.3287148475646973,
                                "y": -1.3824357986450195,
                                "r": 3.000901248873439,
                                "c": 224
                            }
                        ]
                    }
                ]
            },
            "options": {
                "title": {
                    "display": false
                },
                "tooltips": {
                    "callbacks": {
                        "title": [],
                        "afterLabel": []
                    }
                }
            },
            "tooltips": {
                "title": [
                    [
                        "思う（動詞：*）",
                        "できる（動詞：*）",
                        "言う（動詞：*）",
                        "願う（動詞：*）",
                        "つく（動詞：*）",
                        "出る（動詞：*）",
                        "見る（動詞：*）",
                        "やる（動詞：*）",
                        "受ける（動詞：*）",
                        "くださる（動詞：*）",
                        "いただく（動詞：*）",
                        "考える（動詞：*）",
                        "いたす（動詞：*）",
                        "行く（動詞：*）",
                        "出来る（動詞：*）",
                        "頑張る（動詞：*）",
                        "行う（動詞：*）",
                        "負ける（動詞：*）"
                    ],
                    [
                        "コロナウイルス（未定義語：カタカナ）",
                        "コロナウィルス（未定義語：カタカナ）"
                    ],
                    [
                        "コロナ（名詞：普通名詞）",
                        "新型（名詞：普通名詞）",
                        "感染（名詞：サ変名詞）",
                        "人（名詞：普通名詞）",
                        "ウイルス（名詞：普通名詞）",
                        "日本（名詞：地名）",
                        "拡大（名詞：サ変名詞）",
                        "対策（名詞：普通名詞）",
                        "検査（名詞：サ変名詞）",
                        "影響（名詞：サ変名詞）",
                        "今（名詞：時相名詞）",
                        "症（名詞：普通名詞）",
                        "医療（名詞：普通名詞）",
                        "自粛（名詞：サ変名詞）",
                        "事（名詞：普通名詞）",
                        "確認（名詞：サ変名詞）",
                        "国（名詞：普通名詞）",
                        "店（名詞：普通名詞）",
                        "私（名詞：普通名詞）",
                        "世界（名詞：普通名詞）",
                        "中国（名詞：地名）",
                        "防止（名詞：サ変名詞）",
                        "マスク（名詞：普通名詞）",
                        "休業（名詞：サ変名詞）",
                        "情報（名詞：普通名詞）",
                        "対応（名詞：サ変名詞）",
                        "事態（名詞：普通名詞）",
                        "支援（名詞：サ変名詞）",
                        "政府（名詞：普通名詞）",
                        "状況（名詞：普通名詞）",
                        "経済（名詞：普通名詞）",
                        "今日（名詞：時相名詞）",
                        "病院（名詞：普通名詞）",
                        "金（名詞：普通名詞）",
                        "患者（名詞：普通名詞）",
                        "ニュース（名詞：普通名詞）",
                        "営業（名詞：サ変名詞）",
                        "自分（名詞：普通名詞）",
                        "所（名詞：普通名詞）",
                        "東京（名詞：地名）",
                        "気（名詞：普通名詞）",
                        "死亡（名詞：サ変名詞）",
                        "日（名詞：地名）",
                        "方（名詞：普通名詞）",
                        "国民（名詞：普通名詞）",
                        "時間（名詞：時相名詞）",
                        "延期（名詞：サ変名詞）",
                        "皆様（名詞：普通名詞）",
                        "宣言（名詞：サ変名詞）",
                        "発表（名詞：サ変名詞）",
                        "外出（名詞：サ変名詞）",
                        "生活（名詞：サ変名詞）",
                        "判明（名詞：サ変名詞）",
                        "中止（名詞：サ変名詞）",
                        "放送（名詞：サ変名詞）",
                        "会（名詞：普通名詞）",
                        "関係（名詞：サ変名詞）",
                        "問題（名詞：普通名詞）",
                        "変死（名詞：サ変名詞）",
                        "開催（名詞：サ変名詞）",
                        "話（名詞：サ変名詞）",
                        "予定（名詞：サ変名詞）",
                        "県（名詞：普通名詞）",
                        "自宅（名詞：普通名詞）",
                        "危機（名詞：普通名詞）",
                        "死者（名詞：普通名詞）",
                        "臨時（名詞：普通名詞）",
                        "知らせ（名詞：普通名詞）",
                        "協力（名詞：サ変名詞）",
                        "米（名詞：地名）"
                    ],
                    [
                        "ない（形容詞：*）",
                        "緊急だ（形容詞：*）",
                        "いい（形容詞：*）",
                        "必要だ（形容詞：*）",
                        "多い（形容詞：*）",
                        "早い（形容詞：*）",
                        "本当だ（形容詞：*）",
                        "新ただ（形容詞：*）",
                        "可能だ（形容詞：*）",
                        "良い（形容詞：*）"
                    ]
                ],
                "afterLabel": [
                    [
                        "自分（名詞）：1.0<br>いい（形容詞）：0.99<br>事（名詞）：0.99<br>本当だ（形容詞）：0.99<br>見る（動詞）：0.99",
                        "変わる（動詞）：0.99<br>あなた（名詞）：0.99<br>始める（動詞）：0.99<br>ほしい（形容詞）：0.99<br>書く（動詞）：0.99",
                        "ない（形容詞）：1.0<br>いい（形容詞）：0.99<br>人（名詞）：0.97<br>怖い（形容詞）：0.97<br>自分（名詞）：0.97",
                        "理解（名詞）：1.0<br>皆様（名詞）：0.99<br>申し上げる（動詞）：0.99<br>かける（動詞）：0.98<br>協力（名詞）：0.98",
                        "施設（名詞）：0.99<br>実施（名詞）：0.99<br>会（名詞）：0.98<br>更新（名詞）：0.98<br>関する（動詞）：0.98",
                        "高い（形容詞）：0.98<br>同じだ（形容詞）：0.97<br>関係（名詞）：0.97<br>リスク（名詞）：0.97<br>増える（動詞）：0.96",
                        "良い（形容詞）：1.0<br>考える（動詞）：0.99<br>やる（動詞）：0.99<br>本当だ（形容詞）：0.99<br>私（名詞）：0.99",
                        "私（名詞）：1.0<br>良い（形容詞）：1.0<br>今（名詞）：0.99<br>考える（動詞）：0.99<br>見る（動詞）：0.99",
                        "全国（名詞）：0.98<br>伴う（動詞）：0.96<br>対象（名詞）：0.96<br>関する（動詞）：0.95<br>会（名詞）：0.95",
                        "いたす（動詞）：0.99<br>いただく（動詞）：0.99<br>ご覧（名詞）：0.98<br>致す（動詞）：0.98<br>頂く（動詞）：0.98",
                        "致す（動詞）：0.99<br>いたす（動詞）：0.99<br>頂く（動詞）：0.99<br>くださる（動詞）：0.99<br>営業（名詞）：0.99",
                        "良い（形容詞）：1.0<br>やる（動詞）：0.99<br>見る（動詞）：0.99<br>働く（動詞）：0.99<br>私（名詞）：0.99",
                        "いただく（動詞）：0.99<br>くださる（動詞）：0.99<br>致す（動詞）：0.99<br>営業（名詞）：0.98<br>頂く（動詞）：0.98",
                        "仕事（名詞）：0.99<br>気（名詞）：0.99<br>事（名詞）：0.98<br>今（名詞）：0.98<br>私（名詞）：0.98",
                        "早い（形容詞）：0.99<br>何（名詞）：0.99<br>気（名詞）：0.98<br>つける（動詞）：0.98<br>行く（動詞）：0.98",
                        "負ける（動詞）：0.99<br>今日（名詞）：0.98<br>皆さん（名詞）：0.98<br>早い（形容詞）：0.98<br>元気だ（形容詞）：0.98",
                        "サイト（名詞）：0.98<br>状況（名詞）：0.98<br>利用（名詞）：0.97<br>開始（名詞）：0.97<br>公開（名詞）：0.97",
                        "頑張る（動詞）：0.99<br>皆さん（名詞）：0.99<br>今日（名詞）：0.99<br>元気だ（形容詞）：0.98<br>今週（名詞）：0.98"
                    ],
                    [
                        "症（名詞）：0.99<br>新型（名詞）：0.98<br>発表（名詞）：0.97<br>県（名詞）：0.96<br>感染（名詞）：0.95",
                        "現在（名詞）：0.98<br>市（名詞）：0.98<br>施設（名詞）：0.98<br>関する（動詞）：0.98<br>実施（名詞）：0.98"
                    ],
                    [
                        "メディア（名詞）：0.98<br>理由（名詞）：0.97<br>取る（動詞）：0.97<br>首相（名詞）：0.97<br>リスク（名詞）：0.97",
                        "感染（名詞）：0.99<br>コロナウイルス（未定義語）：0.98<br>県（名詞）：0.98<br>症（名詞）：0.97<br>発表（名詞）：0.96",
                        "新型（名詞）：0.99<br>県（名詞）：0.98<br>新ただ（形容詞）：0.97<br>確認（名詞）：0.97<br>発表（名詞）：0.95",
                        "死ぬ（動詞）：0.99<br>ない（形容詞）：0.97<br>言う（動詞）：0.97<br>多い（形容詞）：0.97<br>怖い（形容詞）：0.97",
                        "情報（名詞）：0.98<br>発表（名詞）：0.98<br>コロナウィルス（未定義語）：0.97<br>現在（名詞）：0.97<br>関連（名詞）：0.97",
                        "韓国（名詞）：0.98<br>国（名詞）：0.97<br>政権（名詞）：0.97<br>安倍（名詞）：0.97<br>安倍（名詞）：0.96",
                        "防止（名詞）：0.97<br>伴う（動詞）：0.97<br>関する（動詞）：0.96<br>本日（名詞）：0.96<br>知らせ（名詞）：0.96",
                        "対象（名詞）：0.97<br>事業（名詞）：0.97<br>予算（名詞）：0.96<br>支援（名詞）：0.95<br>地域（名詞）：0.95",
                        "ｐｃｒ（未定義語）：0.99<br>陰性だ（形容詞）：0.97<br>陽性だ（形容詞）：0.96<br>症状（名詞）：0.96<br>キット（名詞）：0.95",
                        "決定（名詞）：0.98<br>延長（名詞）：0.98<br>イベント（名詞）：0.98<br>中止（名詞）：0.98<br>期間（名詞）：0.98",
                        "私（名詞）：1.0<br>やる（動詞）：0.99<br>自分（名詞）：0.99<br>事（名詞）：0.99<br>良い（形容詞）：0.99",
                        "コロナウイルス（未定義語）：0.99<br>発表（名詞）：0.97<br>新型（名詞）：0.97<br>関する（動詞）：0.95<br>ウイルス（名詞）：0.95",
                        "崩壊（名詞）：0.98<br>従事（名詞）：0.93<br>治療（名詞）：0.92<br>韓国（名詞）：0.92<br>関係（名詞）：0.92",
                        "外出（名詞）：0.98<br>急だ（形容詞）：0.95<br>不要だ（形容詞）：0.93<br>飲食（名詞）：0.93<br>補償（名詞）：0.92",
                        "今（名詞）：0.99<br>本当だ（形容詞）：0.99<br>思う（動詞）：0.99<br>私（名詞）：0.99<br>やる（動詞）：0.99",
                        "新ただ（形容詞）：0.99<br>感染（名詞）：0.97<br>例（名詞）：0.97<br>県（名詞）：0.95<br>新型（名詞）：0.93",
                        "韓国（名詞）：0.98<br>日本（名詞）：0.97<br>危機（名詞）：0.96<br>首相（名詞）：0.96<br>中国（名詞）：0.96",
                        "飲食（名詞）：0.99<br>客（名詞）：0.98<br>皆様（名詞）：0.97<br>時間（名詞）：0.97<br>頂く（動詞）：0.97",
                        "やる（動詞）：1.0<br>今（名詞）：1.0<br>良い（形容詞）：1.0<br>本当だ（形容詞）：0.99<br>考える（動詞）：0.99",
                        "問題（名詞）：0.98<br>批判（名詞）：0.98<br>責任（名詞）：0.97<br>政権（名詞）：0.96<br>安倍（名詞）：0.96",
                        "国（名詞）：0.96<br>米（名詞）：0.96<br>韓国（名詞）：0.95<br>武漢（名詞）：0.94<br>米国（名詞）：0.93",
                        "知らせ（名詞）：0.99<br>本日（名詞）：0.98<br>拡大（名詞）：0.97<br>伴う（動詞）：0.97<br>臨時（名詞）：0.97",
                        "使う（動詞）：0.99<br>力（名詞）：0.99<br>あなた（名詞）：0.98<br>聞く（動詞）：0.98<br>始める（動詞）：0.97",
                        "期間（名詞）：0.99<br>店舗（名詞）：0.99<br>営業（名詞）：0.98<br>影響（名詞）：0.97<br>延長（名詞）：0.97",
                        "ウイルス（名詞）：0.98<br>市（名詞）：0.98<br>関連（名詞）：0.97<br>現在（名詞）：0.97<br>関する（動詞）：0.97",
                        "最大だ（形容詞）：0.96<br>対する（動詞）：0.96<br>知事（名詞）：0.94<br>予算（名詞）：0.94<br>求める（動詞）：0.94",
                        "緊急だ（形容詞）：0.99<br>宣言（名詞）：0.99<br>全国（名詞）：0.86<br>受ける（動詞）：0.83<br>要請（名詞）：0.83",
                        "対策（名詞）：0.95<br>向ける（動詞）：0.94<br>事業（名詞）：0.93<br>要請（名詞）：0.93<br>対象（名詞）：0.92",
                        "経済（名詞）：0.99<br>出す（動詞）：0.92<br>国民（名詞）：0.9<br>批判（名詞）：0.89<br>危機（名詞）：0.89",
                        "予防（名詞）：0.99<br>事業（名詞）：0.98<br>公開（名詞）：0.98<br>サイト（名詞）：0.98<br>行う（動詞）：0.98",
                        "政府（名詞）：0.99<br>国民（名詞）：0.93<br>批判（名詞）：0.92<br>危機（名詞）：0.91<br>出す（動詞）：0.91",
                        "元気だ（形容詞）：0.99<br>負ける（動詞）：0.99<br>雨（名詞）：0.99<br>皆さん（名詞）：0.99<br>頑張る（動詞）：0.98",
                        "症状（名詞）：0.98<br>治療（名詞）：0.97<br>陰性だ（形容詞）：0.96<br>入院（名詞）：0.96<br>医師（名詞）：0.96",
                        "給付（名詞）：0.96<br>補償（名詞）：0.93<br>支援（名詞）：0.92<br>学生（名詞）：0.91<br>予算（名詞）：0.9",
                        "陽性だ（形容詞）：0.98<br>ｐｃｒ（未定義語）：0.96<br>接触（名詞）：0.96<br>病院（名詞）：0.95<br>男性（名詞）：0.95",
                        "増加（名詞）：0.99<br>肺炎（名詞）：0.98<br>報道（名詞）：0.98<br>外国（名詞）：0.97<br>接触（名詞）：0.97",
                        "いただく（動詞）：0.99<br>店舗（名詞）：0.98<br>休業（名詞）：0.98<br>頂く（動詞）：0.98<br>いたす（動詞）：0.98",
                        "思う（動詞）：1.0<br>いい（形容詞）：0.99<br>本当だ（形容詞）：0.99<br>今（名詞）：0.99<br>良い（形容詞）：0.99",
                        "研究（名詞）：0.99<br>武漢（名詞）：0.98<br>保健（名詞）：0.96<br>患者（名詞）：0.95<br>楽天（名詞）：0.93",
                        "女性（名詞）：0.98<br>男性（名詞）：0.98<br>速報（名詞）：0.97<br>例（名詞）：0.97<br>接触（名詞）：0.95",
                        "行く（動詞）：0.99<br>つける（動詞）：0.99<br>仕事（名詞）：0.99<br>出来る（動詞）：0.98<br>事（名詞）：0.98",
                        "路上（名詞）：0.98<br>判明（名詞）：0.98<br>変死（名詞）：0.97<br>庁（名詞）：0.97<br>陽性だ（形容詞）：0.97",
                        "おく（動詞）：0.97<br>頂く（動詞）：0.94<br>ライブ（名詞）：0.93<br>客（名詞）：0.92<br>画す（動詞）：0.92",
                        "日（名詞）：0.98<br>ｒｔ（未定義語）：0.98<br>メッセージ（名詞）：0.97<br>雨（名詞）：0.97<br>心（名詞）：0.96",
                        "批判（名詞）：0.99<br>世界（名詞）：0.96<br>政治（名詞）：0.95<br>社会（名詞）：0.95<br>責任（名詞）：0.94",
                        "客（名詞）：0.99<br>かける（動詞）：0.98<br>頂く（動詞）：0.98<br>申し上げる（動詞）：0.98<br>致す（動詞）：0.98",
                        "開催（名詞）：1.0<br>予定（名詞）：1.0<br>中止（名詞）：0.99<br>放送（名詞）：0.99<br>知らせる（動詞）：0.98",
                        "理解（名詞）：0.99<br>申し上げる（動詞）：0.99<br>願う（動詞）：0.99<br>客（名詞）：0.99<br>かける（動詞）：0.99",
                        "緊急だ（形容詞）：0.99<br>事態（名詞）：0.99<br>全国（名詞）：0.9<br>受ける（動詞）：0.88<br>要請（名詞）：0.88",
                        "会見（名詞）：0.98<br>現在（名詞）：0.98<br>ウイルス（名詞）：0.98<br>市（名詞）：0.97<br>県（名詞）：0.97",
                        "自粛（名詞）：0.98<br>急だ（形容詞）：0.98<br>不要だ（形容詞）：0.97<br>願い（名詞）：0.92<br>補償（名詞）：0.92",
                        "議員（名詞）：0.96<br>今回（名詞）：0.96<br>行動（名詞）：0.95<br>必要だ（形容詞）：0.95<br>個人（名詞）：0.95",
                        "相次ぐ（動詞）：1.0<br>庁（名詞）：1.0<br>変死（名詞）：0.99<br>急変（名詞）：0.99<br>容体（名詞）：0.98",
                        "予定（名詞）：1.0<br>開催（名詞）：1.0<br>延期（名詞）：0.99<br>知らせる（動詞）：0.99<br>変更（名詞）：0.99",
                        "延期（名詞）：0.99<br>中止（名詞）：0.98<br>予定（名詞）：0.98<br>開催（名詞）：0.98<br>知らせる（動詞）：0.97",
                        "つく（動詞）：0.98<br>施設（名詞）：0.98<br>実施（名詞）：0.98<br>状況（名詞）：0.97<br>事業（名詞）：0.97",
                        "高い（形容詞）：0.99<br>同じだ（形容詞）：0.98<br>従事（名詞）：0.98<br>首相（名詞）：0.98<br>問題（名詞）：0.97",
                        "責任（名詞）：0.99<br>世界（名詞）：0.98<br>批判（名詞）：0.98<br>同じだ（形容詞）：0.98<br>安倍（名詞）：0.98",
                        "急変（名詞）：1.0<br>相次ぐ（動詞）：0.99<br>庁（名詞）：0.99<br>判明（名詞）：0.99<br>容体（名詞）：0.99",
                        "予定（名詞）：1.0<br>中止（名詞）：1.0<br>延期（名詞）：1.0<br>知らせる（動詞）：0.98<br>放送（名詞）：0.98",
                        "書く（動詞）：0.98<br>毎日（名詞）：0.98<br>変わる（動詞）：0.98<br>手（名詞）：0.98<br>見える（動詞）：0.98",
                        "中止（名詞）：1.0<br>開催（名詞）：1.0<br>延期（名詞）：1.0<br>知らせる（動詞）：0.99<br>当面（名詞）：0.98",
                        "感染（名詞）：0.98<br>新型（名詞）：0.98<br>発表（名詞）：0.97<br>コロナウイルス（未定義語）：0.96<br>会見（名詞）：0.96",
                        "容体（名詞）：0.99<br>急変（名詞）：0.98<br>路上（名詞）：0.97<br>変死（名詞）：0.97<br>庁（名詞）：0.96",
                        "首相（名詞）：0.98<br>責任（名詞）：0.98<br>メディア（名詞）：0.98<br>問題（名詞）：0.97<br>ワクチン（名詞）：0.97",
                        "治療（名詞）：0.97<br>症状（名詞）：0.97<br>肺炎（名詞）：0.96<br>病院（名詞）：0.96<br>死亡（名詞）：0.95",
                        "知らせる（動詞）：0.99<br>当面（名詞）：0.99<br>知らせ（名詞）：0.98<br>期間（名詞）：0.98<br>予定（名詞）：0.98",
                        "防止（名詞）：0.99<br>臨時（名詞）：0.98<br>知らせる（動詞）：0.98<br>当面（名詞）：0.98<br>休止（名詞）：0.98",
                        "致す（動詞）：0.99<br>皆様（名詞）：0.98<br>理解（名詞）：0.98<br>いただく（動詞）：0.98<br>申し上げる（動詞）：0.98",
                        "米国（名詞）：0.98<br>中国（名詞）：0.96<br>国（名詞）：0.95<br>武漢（名詞）：0.95<br>新聞（名詞）：0.95"
                    ],
                    [
                        "言う（動詞）：1.0<br>いい（形容詞）：0.99<br>わかる（動詞）：0.98<br>怖い（形容詞）：0.98<br>しれる（動詞）：0.98",
                        "事態（名詞）：0.99<br>宣言（名詞）：0.99<br>全国（名詞）：0.89<br>受ける（動詞）：0.86<br>要請（名詞）：0.84",
                        "自分（名詞）：0.99<br>思う（動詞）：0.99<br>見る（動詞）：0.99<br>言う（動詞）：0.99<br>良い（形容詞）：0.99",
                        "今回（名詞）：0.98<br>続ける（動詞）：0.98<br>込む（動詞）：0.98<br>取る（動詞）：0.98<br>現場（名詞）：0.97",
                        "死ぬ（動詞）：0.98<br>増える（動詞）：0.97<br>少ない（形容詞）：0.97<br>分かる（動詞）：0.97<br>人（名詞）：0.97",
                        "何（名詞）：0.99<br>出来る（動詞）：0.99<br>皆さん（名詞）：0.99<br>元気だ（形容詞）：0.99<br>大変だ（形容詞）：0.98",
                        "良い（形容詞）：1.0<br>私（名詞）：0.99<br>来る（動詞）：0.99<br>見る（動詞）：0.99<br>やる（動詞）：0.99",
                        "確認（名詞）：0.99<br>例（名詞）：0.99<br>感染（名詞）：0.97<br>県（名詞）：0.96<br>東京（名詞）：0.95",
                        "会社（名詞）：0.98<br>勤務（名詞）：0.97<br>記事（名詞）：0.97<br>報告（名詞）：0.97<br>ー（未定義語）：0.97",
                        "やる（動詞）：1.0<br>見る（動詞）：1.0<br>考える（動詞）：1.0<br>本当だ（形容詞）：1.0<br>私（名詞）：1.0"
                    ]
                ]
            }
        },
        "wc": "2020-04-20_2020-04-21_cv19m.png"
    },
    "entities": {
        "trend": [
            "<blockquote class=\"twitter-tweet\"><p lang=\"ja\" dir=\"ltr\">今日も自宅に居て何もしなかったなー。<br>いえいえ。今日も自宅に居てコロナを阻止しましたよ。<br><br>頑張りましょう。<br>頑張りましょう。<br><br>なんで2回言うねん。<br>なんで3回言えへんねん。</p>&mdash; 松本人志 (@matsu_bouzu) <a href=\"https://twitter.com/matsu_bouzu/status/1252161556671918080?ref_src=twsrc%5Etfw\">April 20, 2020</a></blockquote>\n<script async src=\"https://platform.twitter.com/widgets.js\" charset=\"utf-8\"></script>\n",
            "<blockquote class=\"twitter-tweet\"><p lang=\"ja\" dir=\"ltr\">助けてください…　私たちは50年以上愚直にスモークサーモンをつくって参りましたが、今は大変厳しい状況が続いております。　百貨店は休業、銀座直営店は時短営業で頑張っていますが銀座に人はまばらです。　このままコロナが長引くと、お店の存続すら怪しくなってきます😭</p>&mdash; 【公式】王子サーモン (@Oji_Salmon) <a href=\"https://twitter.com/Oji_Salmon/status/1252047548992241667?ref_src=twsrc%5Etfw\">April 20, 2020</a></blockquote>\n<script async src=\"https://platform.twitter.com/widgets.js\" charset=\"utf-8\"></script>\n",
            "<blockquote class=\"twitter-tweet\"><p lang=\"ja\" dir=\"ltr\">【変死で感染判明相次ぐ 警視庁】<a href=\"https://t.co/SGrlzghYgM\">https://t.co/SGrlzghYgM</a><br><br>路上や自宅などで容体が急変して死亡し警視庁が変死として扱った事案で、死後に、新型コロナウイルスへの感染が判明するケースが、相次いでいることが分かった。医療機関で十分な治療を受けられなかったケースも。</p>&mdash; Yahoo!ニュース (@YahooNewsTopics) <a href=\"https://twitter.com/YahooNewsTopics/status/1252084388885442561?ref_src=twsrc%5Etfw\">April 20, 2020</a></blockquote>\n<script async src=\"https://platform.twitter.com/widgets.js\" charset=\"utf-8\"></script>\n",
            "<blockquote class=\"twitter-tweet\"><p lang=\"ja\" dir=\"ltr\">今後のコロナの行方ですが、そう遠くないところで治療薬が見つかり、「早急な保険適応を」とマスコミがはやしたて、無数の人がそれに群がり、数千人に1人の確率で起きる重篤な副作用を「薬害だ」と騒ぎ立て、「早すぎた認可」と掌返しするマスコミが出てきます。</p>&mdash; ケリー (@jpdrkk) <a href=\"https://twitter.com/jpdrkk/status/1252025935781457922?ref_src=twsrc%5Etfw\">April 20, 2020</a></blockquote>\n<script async src=\"https://platform.twitter.com/widgets.js\" charset=\"utf-8\"></script>\n",
            "<blockquote class=\"twitter-tweet\"><p lang=\"ja\" dir=\"ltr\">コロナ禍の中仕事が増大している宅配業者さんから「１日在宅している場合には【時間指定】はしないでいただけると負担が少なくなりありがたい」という内容を広めてもらえないかというご意見をいただきました！<br><br>大変な中、外でお仕事をしてくださっている宅配業者さんの負担が少しでも減りますように‼️</p>&mdash; 東 友美 🏳️‍🌈（ひがし ともみ）@町田立憲民主党（りっけん） (@higashi_machida) <a href=\"https://twitter.com/higashi_machida/status/1252010329355124736?ref_src=twsrc%5Etfw\">April 19, 2020</a></blockquote>\n<script async src=\"https://platform.twitter.com/widgets.js\" charset=\"utf-8\"></script>\n",
            "<blockquote class=\"twitter-tweet\"><p lang=\"ja\" dir=\"ltr\">12日もスゴいなと思ったら12週間で気絶した<br><br>【国際】マイクロソフト、新型コロナで全従業員に有給休暇12週間追加付与。GAFAも従業員厚遇 <a href=\"https://t.co/FjBPal7GCZ\">https://t.co/FjBPal7GCZ</a></p>&mdash; NATU (@ilya_len) <a href=\"https://twitter.com/ilya_len/status/1252191392077541376?ref_src=twsrc%5Etfw\">April 20, 2020</a></blockquote>\n<script async src=\"https://platform.twitter.com/widgets.js\" charset=\"utf-8\"></script>\n",
            "<blockquote class=\"twitter-tweet\"><p lang=\"ja\" dir=\"ltr\">「ヒーリングっど🖤プリキュア」からのお知らせ<br><br>新型コロナウイルス感染拡大に最大限の配慮をするべく、<br>4月26日（日）より、これまでに放送した話数の中から、厳選したお話をお届けしてまいります。<br><br>第13話以降の放送再開に関しましては、決まり次第お知らせさせて頂きます。 <a href=\"https://t.co/2x3NxcsC9C\">pic.twitter.com/2x3NxcsC9C</a></p>&mdash; 東映アニメーション公式 (@toeianime_info) <a href=\"https://twitter.com/toeianime_info/status/1252039631832403968?ref_src=twsrc%5Etfw\">April 20, 2020</a></blockquote>\n<script async src=\"https://platform.twitter.com/widgets.js\" charset=\"utf-8\"></script>\n",
            "<blockquote class=\"twitter-tweet\"><p lang=\"ja\" dir=\"ltr\">世界中がコロナ一色だけど、こんな大事件も起きている<a href=\"https://t.co/bBT6MmdBAp\">https://t.co/bBT6MmdBAp</a> <a href=\"https://t.co/4JGitgIHcD\">pic.twitter.com/4JGitgIHcD</a></p>&mdash; ザビエル古太郎 (@XavierKotaro) <a href=\"https://twitter.com/XavierKotaro/status/1252076795320393735?ref_src=twsrc%5Etfw\">April 20, 2020</a></blockquote>\n<script async src=\"https://platform.twitter.com/widgets.js\" charset=\"utf-8\"></script>\n",
            "<blockquote class=\"twitter-tweet\"><p lang=\"ja\" dir=\"ltr\">【新型コロナウイルス】緊急事態宣言が解除された後も行動自粛を継続しなければ、約二週間で感染者数が元の数まで増えてしまいます。<br>『行動自粛を継続することが大切です』<br>生物科学専攻・大橋順准教授 <a href=\"https://t.co/mLSIyrFh6F\">pic.twitter.com/mLSIyrFh6F</a></p>&mdash; 東京大学大学院理学系研究科・生物科学専攻 (@UTokyo_BS) <a href=\"https://twitter.com/UTokyo_BS/status/1252217329745682434?ref_src=twsrc%5Etfw\">April 20, 2020</a></blockquote>\n<script async src=\"https://platform.twitter.com/widgets.js\" charset=\"utf-8\"></script>\n",
            "<blockquote class=\"twitter-tweet\"><p lang=\"ja\" dir=\"ltr\">アマビエが注目されていますが、福島県会津には「赤べこ」がいます。赤べこの由来に「平安時代に蔓延した疫病を払った赤い牛の伝説」があり無病息災の縁起物として愛されています。新型コロナウイルスの終息を願って護符を作りました。ご自由にDLください。みなさんの不安が少しでも和らぎますように。 <a href=\"https://t.co/9ZFxQ4eYHa\">pic.twitter.com/9ZFxQ4eYHa</a></p>&mdash; 土津神社‐こどもと出世の神さま‐ (@hanitsu_jinja) <a href=\"https://twitter.com/hanitsu_jinja/status/1252100336728150016?ref_src=twsrc%5Etfw\">April 20, 2020</a></blockquote>\n<script async src=\"https://platform.twitter.com/widgets.js\" charset=\"utf-8\"></script>\n"
        ],
        "hashtag": [
            {
                "text": "新型コロナウイルス",
                "count": 92,
                "vertified_count": 43
            },
            {
                "text": "コロナ",
                "count": 78,
                "vertified_count": 5
            },
            {
                "text": "nhk_news",
                "count": 69,
                "vertified_count": 69
            },
            {
                "text": "新型コロナ",
                "count": 48,
                "vertified_count": 17
            },
            {
                "text": "新型肺炎",
                "count": 42,
                "vertified_count": 35
            },
            {
                "text": "日テレNEWS24",
                "count": 28,
                "vertified_count": 8
            },
            {
                "text": "拡散希望",
                "count": 25,
                "vertified_count": 0
            },
            {
                "text": "神戸新聞",
                "count": 24,
                "vertified_count": 24
            },
            {
                "text": "コロナに負けるな",
                "count": 24,
                "vertified_count": 2
            },
            {
                "text": "パンデミック",
                "count": 21,
                "vertified_count": 21
            }
        ],
        "url": [
            {
                "domain": "twitter.com",
                "count": 718,
                "vertified_count": 53
            },
            {
                "domain": "www3.nhk.or.jp",
                "count": 224,
                "vertified_count": 147
            },
            {
                "domain": "headlines.yahoo.co.jp",
                "count": 161,
                "vertified_count": 9
            },
            {
                "domain": "youtu.be",
                "count": 135,
                "vertified_count": 19
            },
            {
                "domain": "www.jiji.com",
                "count": 108,
                "vertified_count": 70
            },
            {
                "domain": "bit.ly",
                "count": 98,
                "vertified_count": 48
            },
            {
                "domain": "www.asahi.com",
                "count": 98,
                "vertified_count": 41
            },
            {
                "domain": "news.yahoo.co.jp",
                "count": 83,
                "vertified_count": 8
            },
            {
                "domain": "www.nikkei.com",
                "count": 83,
                "vertified_count": 32
            },
            {
                "domain": "mainichi.jp",
                "count": 82,
                "vertified_count": 39
            }
        ]
    }
}