{
    "home": {
        "overview": {
            "CVTgraph_cv": {
                "type": "bar",
                "data": {
                    "type": "bar",
                    "labels": [
                        "03/23",
                        "03/24",
                        "03/25",
                        "03/26",
                        "03/27",
                        "03/28",
                        "03/29",
                        "03/30",
                        "03/31",
                        "04/01",
                        "04/02",
                        "04/03",
                        "04/04",
                        "04/05",
                        "04/06",
                        "04/07",
                        "04/08",
                        "04/09",
                        "04/10",
                        "04/11",
                        "04/12",
                        "04/13",
                        "04/14",
                        "04/15",
                        "04/16",
                        "04/17",
                        "04/18",
                        "04/19",
                        "04/20",
                        "04/21",
                        "04/22",
                        "04/23",
                        "04/24",
                        "04/25",
                        "04/26",
                        "04/27",
                        "04/28",
                        "04/29",
                        "04/30",
                        "05/01",
                        "05/02",
                        "05/03",
                        "05/04",
                        "05/05",
                        "05/06",
                        "05/07",
                        "05/08",
                        "05/09",
                        "05/10",
                        "05/11",
                        "05/12",
                        "05/13",
                        "05/14",
                        "05/15",
                        "05/16",
                        "05/17",
                        "05/18",
                        "05/19",
                        "05/20",
                        "05/21"
                    ],
                    "datasets": [
                        {
                            "label": "感染者数",
                            "type": "bar",
                            "data": [
                                38,
                                65,
                                93,
                                95,
                                104,
                                194,
                                173,
                                67,
                                219,
                                199,
                                234,
                                314,
                                336,
                                378,
                                248,
                                352,
                                498,
                                579,
                                655,
                                714,
                                510,
                                390,
                                454,
                                478,
                                586,
                                629,
                                566,
                                391,
                                367,
                                376,
                                420,
                                468,
                                445,
                                362,
                                207,
                                191,
                                274,
                                234,
                                204,
                                264,
                                293,
                                221,
                                174,
                                123,
                                108,
                                82,
                                101,
                                98,
                                49,
                                76,
                                148,
                                54,
                                114,
                                44,
                                46,
                                50,
                                19,
                                33,
                                35,
                                43
                            ],
                            "backgroundColor": [
                                [
                                    "rgb(227, 227, 227)",
                                    "rgb(227, 227, 227)",
                                    "rgb(227, 227, 227)",
                                    "rgb(227, 227, 227)",
                                    "rgb(227, 227, 227)",
                                    "rgb(227, 227, 227)",
                                    "rgb(227, 227, 227)",
                                    "rgb(227, 227, 227)",
                                    "rgb(227, 227, 227)",
                                    "rgb(227, 227, 227)",
                                    "rgb(227, 227, 227)",
                                    "rgb(227, 227, 227)",
                                    "rgb(227, 227, 227)",
                                    "rgb(227, 227, 227)",
                                    "rgb(227, 227, 227)",
                                    "rgb(227, 227, 227)",
                                    "rgb(227, 227, 227)",
                                    "rgb(227, 227, 227)",
                                    "rgb(227, 227, 227)",
                                    "rgb(227, 227, 227)",
                                    "rgb(227, 227, 227)",
                                    "rgb(227, 227, 227)",
                                    "rgb(227, 227, 227)",
                                    "rgb(227, 227, 227)",
                                    "rgb(227, 227, 227)",
                                    "rgb(227, 227, 227)",
                                    "rgb(227, 227, 227)",
                                    "rgb(227, 227, 227)",
                                    "rgb(227, 227, 227)",
                                    "rgb(227, 227, 227)",
                                    "rgb(227, 227, 227)",
                                    "rgb(227, 227, 227)",
                                    "rgb(227, 227, 227)",
                                    "rgb(227, 227, 227)",
                                    "rgb(227, 227, 227)",
                                    "rgb(227, 227, 227)",
                                    "rgb(227, 227, 227)",
                                    "rgb(227, 227, 227)",
                                    "rgb(227, 227, 227)",
                                    "rgb(227, 227, 227)",
                                    "rgb(227, 227, 227)",
                                    "rgb(227, 227, 227)",
                                    "rgb(227, 227, 227)",
                                    "rgb(227, 227, 227)",
                                    "rgb(227, 227, 227)",
                                    "rgb(227, 227, 227)",
                                    "rgb(227, 227, 227)",
                                    "rgb(227, 227, 227)",
                                    "rgb(227, 227, 227)",
                                    "rgb(227, 227, 227)",
                                    "rgb(227, 227, 227)",
                                    "rgb(227, 227, 227)",
                                    "rgb(227, 227, 227)",
                                    "rgb(227, 227, 227)",
                                    "rgb(227, 227, 227)",
                                    "rgb(227, 227, 227)",
                                    "rgb(227, 227, 227)",
                                    "rgb(227, 227, 227)",
                                    "rgb(227, 227, 227)",
                                    "rgb(227, 227, 227)"
                                ]
                            ],
                            "yAxisID": "y_1",
                            "order": 2
                        },
                        {
                            "label": "RT>=10∧FAV>=10のツイート数",
                            "type": "line",
                            "data": [
                                0,
                                0,
                                0,
                                0,
                                0,
                                0,
                                8674,
                                13313,
                                11351,
                                11226,
                                10491,
                                11797,
                                10045,
                                9261,
                                10615,
                                12492,
                                11527,
                                10434,
                                10826,
                                9511,
                                8755,
                                9400,
                                9579,
                                9619,
                                9239,
                                9509,
                                8260,
                                8065,
                                9034,
                                8807,
                                8946,
                                9401,
                                9053,
                                7695,
                                7150,
                                7840,
                                7515,
                                5466,
                                7766,
                                8041,
                                6840,
                                6553,
                                6342,
                                6670,
                                6308,
                                6476,
                                6483,
                                5556,
                                5424,
                                5569,
                                5477,
                                6024,
                                5922,
                                5906,
                                4671,
                                4011,
                                4674,
                                4956,
                                5007,
                                4528
                            ],
                            "borderColor": "#AAB6FB",
                            "pointBackgroundColor": "#AAB6FB",
                            "pointBorderColor": "#AAB6FB",
                            "fill": false,
                            "yAxisID": "y_2",
                            "order": 1
                        }
                    ]
                },
                "options": {
                    "legend": {
                        "display": false
                    },
                    "title": {
                        "display": false
                    },
                    "scales": {
                        "yAxes": [
                            {
                                "id": "y_1",
                                "type": "linear",
                                "position": "left"
                            },
                            {
                                "id": "y_2",
                                "type": "linear",
                                "position": "right",
                                "gridLines": {
                                    "drawOnChartArea": false
                                }
                            }
                        ]
                    },
                    "tooltips": {
                        "callbacks": {
                            "label": []
                        }
                    }
                }
            }
        },
        "Adata": {
            "infected": {
                "count": 16339,
                "period": "2020-02-05 ~ 2020-05-21"
            },
            "tweet": {
                "count": 434100,
                "period": "2020-03-29 ~ 2020-05-21"
            },
            "vocabulary": {
                "count": 138850,
                "period": "2020-03-29 ~ 2020-05-21"
            }
        }
    },
    "words": {
        "words": {
            "words_pn": {
                "count": 22451176,
                "count_unk": 138850
            },
            "words_cv": {
                "type": "bar",
                "data": {
                    "type": "bar",
                    "labels": [
                        "03/29",
                        "03/30",
                        "03/31",
                        "04/01",
                        "04/02",
                        "04/03",
                        "04/04",
                        "04/05",
                        "04/06",
                        "04/07",
                        "04/08",
                        "04/09",
                        "04/10",
                        "04/11",
                        "04/12",
                        "04/13",
                        "04/14",
                        "04/15",
                        "04/16",
                        "04/17",
                        "04/18",
                        "04/19",
                        "04/20",
                        "04/21",
                        "04/22",
                        "04/23",
                        "04/24",
                        "04/25",
                        "04/26",
                        "04/27",
                        "04/28",
                        "04/29",
                        "04/30",
                        "05/01",
                        "05/02",
                        "05/03",
                        "05/04",
                        "05/05",
                        "05/06",
                        "05/07",
                        "05/08",
                        "05/09",
                        "05/10",
                        "05/11",
                        "05/12",
                        "05/13",
                        "05/14",
                        "05/15",
                        "05/16",
                        "05/17",
                        "05/18",
                        "05/19",
                        "05/20"
                    ],
                    "datasets": [
                        {
                            "label": "ツイート数",
                            "type": "bar",
                            "data": [
                                8674,
                                13313,
                                11351,
                                11226,
                                10491,
                                11797,
                                10045,
                                9261,
                                10615,
                                12492,
                                11527,
                                10434,
                                10826,
                                9511,
                                8755,
                                9400,
                                9579,
                                9619,
                                9239,
                                9509,
                                8260,
                                8065,
                                9034,
                                8807,
                                8946,
                                9401,
                                9053,
                                7695,
                                7150,
                                7840,
                                7515,
                                5466,
                                7766,
                                8041,
                                6840,
                                6553,
                                6342,
                                6670,
                                6308,
                                6476,
                                6483,
                                5556,
                                5424,
                                5569,
                                5477,
                                6024,
                                5922,
                                5906,
                                4671,
                                4011,
                                4674,
                                4956,
                                5007
                            ],
                            "backgroundColor": "#AAB6FB",
                            "yAxisID": "y_2",
                            "order": 3
                        },
                        {
                            "label": "総出現語数",
                            "type": "line",
                            "data": [
                                443770,
                                679693,
                                583079,
                                570281,
                                538449,
                                599675,
                                509008,
                                486740,
                                547170,
                                649322,
                                583900,
                                538191,
                                553032,
                                494778,
                                450646,
                                482813,
                                489978,
                                486433,
                                480186,
                                496999,
                                425082,
                                421825,
                                473992,
                                456663,
                                464310,
                                481773,
                                469797,
                                398271,
                                379549,
                                404155,
                                388820,
                                285055,
                                407909,
                                419091,
                                359546,
                                346585,
                                329791,
                                351077,
                                335651,
                                337618,
                                337319,
                                287864,
                                286689,
                                291466,
                                281755,
                                309134,
                                301082,
                                302773,
                                243439,
                                206913,
                                245947,
                                258650,
                                261401
                            ],
                            "borderColor": "#FB7B8E",
                            "pointBackgroundColor": "#FB7B8E",
                            "pointBorderColor": "#FB7B8E",
                            "fill": false,
                            "yAxisID": "y_1",
                            "order": 1
                        },
                        {
                            "label": "異なり語数",
                            "type": "line",
                            "data": [
                                21956,
                                24543,
                                24294,
                                23990,
                                23469,
                                24435,
                                22867,
                                22453,
                                23869,
                                25559,
                                24963,
                                23987,
                                24410,
                                23330,
                                22457,
                                23021,
                                23229,
                                22725,
                                23019,
                                23618,
                                22255,
                                22173,
                                23241,
                                22720,
                                22571,
                                23088,
                                22794,
                                21596,
                                20959,
                                21464,
                                20762,
                                18064,
                                21543,
                                21843,
                                20272,
                                19845,
                                19179,
                                19938,
                                19451,
                                19430,
                                19428,
                                18303,
                                17777,
                                18350,
                                18026,
                                18461,
                                18174,
                                18289,
                                17100,
                                15591,
                                16842,
                                17099,
                                17172
                            ],
                            "borderColor": "#FDC094",
                            "pointBackgroundColor": "#FDC094",
                            "pointBorderColor": "#FDC094",
                            "fill": false,
                            "yAxisID": "y_1",
                            "order": 2
                        }
                    ]
                },
                "options": {
                    "legend": {
                        "display": false
                    },
                    "title": {
                        "display": false
                    },
                    "scales": {
                        "yAxes": [
                            {
                                "id": "y_1",
                                "type": "linear",
                                "position": "left"
                            },
                            {
                                "id": "y_2",
                                "type": "linear",
                                "position": "right",
                                "gridLines": {
                                    "drawOnChartArea": false
                                }
                            }
                        ]
                    },
                    "tooltips": {
                        "callbacks": {
                            "label": []
                        }
                    }
                }
            }
        },
        "posi-nega": {
            "type": "doughnut",
            "data": {
                "labels": [
                    "positive",
                    "neutral",
                    "negative"
                ],
                "datasets": [
                    {
                        "label": "",
                        "data": [
                            511696,
                            706150,
                            1195005
                        ],
                        "backgroundColor": [
                            "#FB7B8E",
                            "#FDC094",
                            "#6096FD"
                        ]
                    }
                ]
            },
            "options": {
                "legend": {
                    "display": false
                },
                "title": {
                    "display": false
                },
                "tooltips": {
                    "callbacks": {
                        "label": []
                    }
                }
            }
        },
        "count": [
            {
                "原形": "コロナ",
                "品詞": "名詞",
                "品詞細分類": "普通名詞",
                "出現回数": 383412
            },
            {
                "原形": "新型",
                "品詞": "名詞",
                "品詞細分類": "普通名詞",
                "出現回数": 187595
            },
            {
                "原形": "感染",
                "品詞": "名詞",
                "品詞細分類": "サ変名詞",
                "出現回数": 166917
            },
            {
                "原形": "コロナウイルス",
                "品詞": "未定義語",
                "品詞細分類": "カタカナ",
                "出現回数": 69755
            },
            {
                "原形": "人",
                "品詞": "名詞",
                "品詞細分類": "普通名詞",
                "出現回数": 68402
            },
            {
                "原形": "ウイルス",
                "品詞": "名詞",
                "品詞細分類": "普通名詞",
                "出現回数": 59709
            },
            {
                "原形": "日本",
                "品詞": "名詞",
                "品詞細分類": "地名",
                "出現回数": 51191
            },
            {
                "原形": "対策",
                "品詞": "名詞",
                "品詞細分類": "普通名詞",
                "出現回数": 47540
            },
            {
                "原形": "思う",
                "品詞": "動詞",
                "品詞細分類": "*",
                "出現回数": 43709
            },
            {
                "原形": "拡大",
                "品詞": "名詞",
                "品詞細分類": "サ変名詞",
                "出現回数": 43507
            },
            {
                "原形": "できる",
                "品詞": "動詞",
                "品詞細分類": "*",
                "出現回数": 34236
            },
            {
                "原形": "影響",
                "品詞": "名詞",
                "品詞細分類": "サ変名詞",
                "出現回数": 34106
            },
            {
                "原形": "ない",
                "品詞": "形容詞",
                "品詞細分類": "*",
                "出現回数": 33829
            },
            {
                "原形": "言う",
                "品詞": "動詞",
                "品詞細分類": "*",
                "出現回数": 32816
            },
            {
                "原形": "今",
                "品詞": "名詞",
                "品詞細分類": "時相名詞",
                "出現回数": 30095
            },
            {
                "原形": "症",
                "品詞": "名詞",
                "品詞細分類": "普通名詞",
                "出現回数": 28797
            },
            {
                "原形": "検査",
                "品詞": "名詞",
                "品詞細分類": "サ変名詞",
                "出現回数": 28618
            },
            {
                "原形": "つく",
                "品詞": "動詞",
                "品詞細分類": "*",
                "出現回数": 28019
            },
            {
                "原形": "自粛",
                "品詞": "名詞",
                "品詞細分類": "サ変名詞",
                "出現回数": 27564
            },
            {
                "原形": "願う",
                "品詞": "動詞",
                "品詞細分類": "*",
                "出現回数": 25519
            },
            {
                "原形": "医療",
                "品詞": "名詞",
                "品詞細分類": "普通名詞",
                "出現回数": 25046
            },
            {
                "原形": "事",
                "品詞": "名詞",
                "品詞細分類": "普通名詞",
                "出現回数": 24371
            },
            {
                "原形": "国",
                "品詞": "名詞",
                "品詞細分類": "普通名詞",
                "出現回数": 24082
            },
            {
                "原形": "緊急だ",
                "品詞": "形容詞",
                "品詞細分類": "*",
                "出現回数": 23510
            },
            {
                "原形": "出る",
                "品詞": "動詞",
                "品詞細分類": "*",
                "出現回数": 22041
            },
            {
                "原形": "確認",
                "品詞": "名詞",
                "品詞細分類": "サ変名詞",
                "出現回数": 21848
            },
            {
                "原形": "世界",
                "品詞": "名詞",
                "品詞細分類": "普通名詞",
                "出現回数": 21791
            },
            {
                "原形": "見る",
                "品詞": "動詞",
                "品詞細分類": "*",
                "出現回数": 20882
            },
            {
                "原形": "事態",
                "品詞": "名詞",
                "品詞細分類": "普通名詞",
                "出現回数": 20609
            },
            {
                "原形": "政府",
                "品詞": "名詞",
                "品詞細分類": "普通名詞",
                "出現回数": 20030
            },
            {
                "原形": "やる",
                "品詞": "動詞",
                "品詞細分類": "*",
                "出現回数": 19964
            },
            {
                "原形": "防止",
                "品詞": "名詞",
                "品詞細分類": "サ変名詞",
                "出現回数": 19594
            },
            {
                "原形": "東京",
                "品詞": "名詞",
                "品詞細分類": "地名",
                "出現回数": 19478
            },
            {
                "原形": "私",
                "品詞": "名詞",
                "品詞細分類": "普通名詞",
                "出現回数": 19258
            },
            {
                "原形": "マスク",
                "品詞": "名詞",
                "品詞細分類": "普通名詞",
                "出現回数": 18970
            },
            {
                "原形": "情報",
                "品詞": "名詞",
                "品詞細分類": "普通名詞",
                "出現回数": 18643
            },
            {
                "原形": "店",
                "品詞": "名詞",
                "品詞細分類": "普通名詞",
                "出現回数": 18593
            },
            {
                "原形": "対応",
                "品詞": "名詞",
                "品詞細分類": "サ変名詞",
                "出現回数": 18569
            },
            {
                "原形": "中国",
                "品詞": "名詞",
                "品詞細分類": "地名",
                "出現回数": 18308
            },
            {
                "原形": "状況",
                "品詞": "名詞",
                "品詞細分類": "普通名詞",
                "出現回数": 18195
            },
            {
                "原形": "受ける",
                "品詞": "動詞",
                "品詞細分類": "*",
                "出現回数": 17901
            },
            {
                "原形": "経済",
                "品詞": "名詞",
                "品詞細分類": "普通名詞",
                "出現回数": 17874
            },
            {
                "原形": "中止",
                "品詞": "名詞",
                "品詞細分類": "サ変名詞",
                "出現回数": 17263
            },
            {
                "原形": "休業",
                "品詞": "名詞",
                "品詞細分類": "サ変名詞",
                "出現回数": 17248
            },
            {
                "原形": "金",
                "品詞": "名詞",
                "品詞細分類": "普通名詞",
                "出現回数": 16853
            },
            {
                "原形": "支援",
                "品詞": "名詞",
                "品詞細分類": "サ変名詞",
                "出現回数": 16708
            },
            {
                "原形": "ニュース",
                "品詞": "名詞",
                "品詞細分類": "普通名詞",
                "出現回数": 16285
            },
            {
                "原形": "今日",
                "品詞": "名詞",
                "品詞細分類": "時相名詞",
                "出現回数": 16163
            },
            {
                "原形": "宣言",
                "品詞": "名詞",
                "品詞細分類": "サ変名詞",
                "出現回数": 16039
            },
            {
                "原形": "国民",
                "品詞": "名詞",
                "品詞細分類": "普通名詞",
                "出現回数": 15978
            },
            {
                "原形": "病院",
                "品詞": "名詞",
                "品詞細分類": "普通名詞",
                "出現回数": 15795
            },
            {
                "原形": "患者",
                "品詞": "名詞",
                "品詞細分類": "普通名詞",
                "出現回数": 15790
            },
            {
                "原形": "発表",
                "品詞": "名詞",
                "品詞細分類": "サ変名詞",
                "出現回数": 15682
            },
            {
                "原形": "いい",
                "品詞": "形容詞",
                "品詞細分類": "*",
                "出現回数": 15677
            },
            {
                "原形": "行く",
                "品詞": "動詞",
                "品詞細分類": "*",
                "出現回数": 15224
            },
            {
                "原形": "自分",
                "品詞": "名詞",
                "品詞細分類": "普通名詞",
                "出現回数": 15013
            },
            {
                "原形": "いただく",
                "品詞": "動詞",
                "品詞細分類": "*",
                "出現回数": 14962
            },
            {
                "原形": "営業",
                "品詞": "名詞",
                "品詞細分類": "サ変名詞",
                "出現回数": 14934
            },
            {
                "原形": "予定",
                "品詞": "名詞",
                "品詞細分類": "サ変名詞",
                "出現回数": 14926
            },
            {
                "原形": "考える",
                "品詞": "動詞",
                "品詞細分類": "*",
                "出現回数": 14595
            },
            {
                "原形": "開催",
                "品詞": "名詞",
                "品詞細分類": "サ変名詞",
                "出現回数": 14275
            },
            {
                "原形": "方",
                "品詞": "名詞",
                "品詞細分類": "普通名詞",
                "出現回数": 13876
            },
            {
                "原形": "生活",
                "品詞": "名詞",
                "品詞細分類": "サ変名詞",
                "出現回数": 13773
            },
            {
                "原形": "延期",
                "品詞": "名詞",
                "品詞細分類": "サ変名詞",
                "出現回数": 13749
            },
            {
                "原形": "気",
                "品詞": "名詞",
                "品詞細分類": "普通名詞",
                "出現回数": 13705
            },
            {
                "原形": "いたす",
                "品詞": "動詞",
                "品詞細分類": "*",
                "出現回数": 13699
            },
            {
                "原形": "外出",
                "品詞": "名詞",
                "品詞細分類": "サ変名詞",
                "出現回数": 13539
            },
            {
                "原形": "コロナウィルス",
                "品詞": "未定義語",
                "品詞細分類": "カタカナ",
                "出現回数": 13473
            },
            {
                "原形": "くださる",
                "品詞": "動詞",
                "品詞細分類": "*",
                "出現回数": 13314
            },
            {
                "原形": "日",
                "品詞": "名詞",
                "品詞細分類": "地名",
                "出現回数": 13055
            },
            {
                "原形": "会",
                "品詞": "名詞",
                "品詞細分類": "普通名詞",
                "出現回数": 12862
            },
            {
                "原形": "所",
                "品詞": "名詞",
                "品詞細分類": "普通名詞",
                "出現回数": 12799
            },
            {
                "原形": "必要だ",
                "品詞": "形容詞",
                "品詞細分類": "*",
                "出現回数": 12572
            },
            {
                "原形": "皆様",
                "品詞": "名詞",
                "品詞細分類": "普通名詞",
                "出現回数": 12532
            },
            {
                "原形": "多い",
                "品詞": "形容詞",
                "品詞細分類": "*",
                "出現回数": 12347
            },
            {
                "原形": "致す",
                "品詞": "動詞",
                "品詞細分類": "*",
                "出現回数": 12238
            },
            {
                "原形": "本当だ",
                "品詞": "形容詞",
                "品詞細分類": "*",
                "出現回数": 12204
            },
            {
                "原形": "知らせ",
                "品詞": "名詞",
                "品詞細分類": "普通名詞",
                "出現回数": 12169
            },
            {
                "原形": "新ただ",
                "品詞": "形容詞",
                "品詞細分類": "*",
                "出現回数": 11965
            },
            {
                "原形": "可能だ",
                "品詞": "形容詞",
                "品詞細分類": "*",
                "出現回数": 11857
            },
            {
                "原形": "時間",
                "品詞": "名詞",
                "品詞細分類": "時相名詞",
                "出現回数": 11823
            },
            {
                "原形": "頂く",
                "品詞": "動詞",
                "品詞細分類": "*",
                "出現回数": 11754
            },
            {
                "原形": "出来る",
                "品詞": "動詞",
                "品詞細分類": "*",
                "出現回数": 11670
            },
            {
                "原形": "早い",
                "品詞": "形容詞",
                "品詞細分類": "*",
                "出現回数": 11417
            },
            {
                "原形": "関係",
                "品詞": "名詞",
                "品詞細分類": "サ変名詞",
                "出現回数": 11408
            },
            {
                "原形": "危機",
                "品詞": "名詞",
                "品詞細分類": "普通名詞",
                "出現回数": 11347
            },
            {
                "原形": "良い",
                "品詞": "形容詞",
                "品詞細分類": "*",
                "出現回数": 11046
            },
            {
                "原形": "県",
                "品詞": "名詞",
                "品詞細分類": "普通名詞",
                "出現回数": 11013
            },
            {
                "原形": "問題",
                "品詞": "名詞",
                "品詞細分類": "普通名詞",
                "出現回数": 10989
            },
            {
                "原形": "死亡",
                "品詞": "名詞",
                "品詞細分類": "サ変名詞",
                "出現回数": 10892
            },
            {
                "原形": "行う",
                "品詞": "動詞",
                "品詞細分類": "*",
                "出現回数": 10841
            },
            {
                "原形": "本日",
                "品詞": "名詞",
                "品詞細分類": "時相名詞",
                "出現回数": 10505
            },
            {
                "原形": "死者",
                "品詞": "名詞",
                "品詞細分類": "普通名詞",
                "出現回数": 10307
            },
            {
                "原形": "仕事",
                "品詞": "名詞",
                "品詞細分類": "サ変名詞",
                "出現回数": 10194
            },
            {
                "原形": "客",
                "品詞": "名詞",
                "品詞細分類": "普通名詞",
                "出現回数": 10117
            },
            {
                "原形": "出す",
                "品詞": "動詞",
                "品詞細分類": "*",
                "出現回数": 10039
            },
            {
                "原形": "大阪",
                "品詞": "名詞",
                "品詞細分類": "地名",
                "出現回数": 10005
            },
            {
                "原形": "来る",
                "品詞": "動詞",
                "品詞細分類": "*",
                "出現回数": 9962
            },
            {
                "原形": "米",
                "品詞": "名詞",
                "品詞細分類": "地名",
                "出現回数": 9869
            },
            {
                "原形": "協力",
                "品詞": "名詞",
                "品詞細分類": "サ変名詞",
                "出現回数": 9864
            }
        ],
        "w2v": {
            "type": "bubble",
            "data": {
                "datasets": [
                    {
                        "label": "動詞",
                        "backgroundColor": "#6096FD",
                        "data": [
                            {
                                "x": -5.2361273765563965,
                                "y": 3.5242810249328613,
                                "r": 3.6342290682857357,
                                "c": 43709
                            },
                            {
                                "x": -2.976926326751709,
                                "y": 2.601860284805298,
                                "r": 3.456712390375534,
                                "c": 34236
                            },
                            {
                                "x": -6.696639060974121,
                                "y": 1.3747543096542358,
                                "r": 3.4301026909527024,
                                "c": 32816
                            },
                            {
                                "x": 3.1601500511169434,
                                "y": -2.190242290496826,
                                "r": 3.3402106288883893,
                                "c": 28019
                            },
                            {
                                "x": 3.1384830474853516,
                                "y": 8.36854362487793,
                                "r": 3.2933625665242485,
                                "c": 25519
                            },
                            {
                                "x": -4.575843811035156,
                                "y": -0.2433299422264099,
                                "r": 3.228187542163256,
                                "c": 22041
                            },
                            {
                                "x": -5.322132587432861,
                                "y": 1.4892945289611816,
                                "r": 3.2064687804512406,
                                "c": 20882
                            },
                            {
                                "x": -5.74963903427124,
                                "y": 2.9315695762634277,
                                "r": 3.189266171951128,
                                "c": 19964
                            },
                            {
                                "x": 3.185420513153076,
                                "y": -2.423741340637207,
                                "r": 3.150607150888239,
                                "c": 17901
                            },
                            {
                                "x": -5.479371070861816,
                                "y": 4.3164873123168945,
                                "r": 3.1004422457087175,
                                "c": 15224
                            },
                            {
                                "x": 7.475368499755859,
                                "y": 5.2297043800354,
                                "r": 3.0955325687729554,
                                "c": 14962
                            },
                            {
                                "x": -3.543063163757324,
                                "y": 2.9925954341888428,
                                "r": 3.0886552732178996,
                                "c": 14595
                            },
                            {
                                "x": 10.13589859008789,
                                "y": 5.14761209487915,
                                "r": 3.0718649276665917,
                                "c": 13699
                            },
                            {
                                "x": 4.177149772644043,
                                "y": 5.123875617980957,
                                "r": 3.064650326062514,
                                "c": 13314
                            },
                            {
                                "x": 8.001319885253906,
                                "y": 8.02997875213623,
                                "r": 3.044486920020988,
                                "c": 12238
                            },
                            {
                                "x": 6.419647216796875,
                                "y": 6.320743083953857,
                                "r": 3.0354171351472905,
                                "c": 11754
                            },
                            {
                                "x": -3.3823442459106445,
                                "y": 5.287917137145996,
                                "r": 3.0338430402518552,
                                "c": 11670
                            },
                            {
                                "x": 2.105015754699707,
                                "y": -1.378270149230957,
                                "r": 3.018308222771906,
                                "c": 10841
                            },
                            {
                                "x": -4.472614288330078,
                                "y": -0.09797534346580505,
                                "r": 3.00327936436549,
                                "c": 10039
                            },
                            {
                                "x": -4.133208751678467,
                                "y": 3.868898391723633,
                                "r": 3.0018364440446743,
                                "c": 9962
                            }
                        ]
                    },
                    {
                        "label": "未定義語",
                        "backgroundColor": "#FDC094",
                        "data": [
                            {
                                "x": 5.506694793701172,
                                "y": -6.364109992980957,
                                "r": 4.122310921220299,
                                "c": 69755
                            },
                            {
                                "x": 4.117951393127441,
                                "y": -1.9157488346099854,
                                "r": 3.0676298628288734,
                                "c": 13473
                            }
                        ]
                    },
                    {
                        "label": "名詞",
                        "backgroundColor": "#FF9190",
                        "data": [
                            {
                                "x": -1.9352526664733887,
                                "y": -0.976953387260437,
                                "r": 10.0,
                                "c": 383412
                            },
                            {
                                "x": 4.007696151733398,
                                "y": -5.587597846984863,
                                "r": 6.330541188816431,
                                "c": 187595
                            },
                            {
                                "x": 3.284517526626587,
                                "y": -4.810307502746582,
                                "r": 5.943051495390151,
                                "c": 166917
                            },
                            {
                                "x": -6.880239486694336,
                                "y": 0.6394574642181396,
                                "r": 4.096956749868825,
                                "c": 68402
                            },
                            {
                                "x": 2.059459686279297,
                                "y": -3.1561126708984375,
                                "r": 3.9340566674162356,
                                "c": 59709
                            },
                            {
                                "x": -4.655751705169678,
                                "y": -2.860220432281494,
                                "r": 3.7744359493291357,
                                "c": 51191
                            },
                            {
                                "x": 0.4853566288948059,
                                "y": -1.5827445983886719,
                                "r": 3.7060190390525447,
                                "c": 47540
                            },
                            {
                                "x": 7.57802677154541,
                                "y": -3.19181752204895,
                                "r": 3.6304437448467133,
                                "c": 43507
                            },
                            {
                                "x": 2.3841354846954346,
                                "y": 2.3463876247406006,
                                "r": 3.4542762911325986,
                                "c": 34106
                            },
                            {
                                "x": -4.70728874206543,
                                "y": 2.9727790355682373,
                                "r": 3.3791132598755715,
                                "c": 30095
                            },
                            {
                                "x": 6.1982831954956055,
                                "y": -6.258030891418457,
                                "r": 3.3547897458961096,
                                "c": 28797
                            },
                            {
                                "x": -4.236901760101318,
                                "y": -5.316866397857666,
                                "r": 3.351435424630837,
                                "c": 28618
                            },
                            {
                                "x": 0.38676488399505615,
                                "y": 3.7264602184295654,
                                "r": 3.3316842815381156,
                                "c": 27564
                            },
                            {
                                "x": -3.2722082138061523,
                                "y": -3.9425292015075684,
                                "r": 3.284498913124953,
                                "c": 25046
                            },
                            {
                                "x": -3.9085137844085693,
                                "y": 3.705881118774414,
                                "r": 3.2718499362866353,
                                "c": 24371
                            },
                            {
                                "x": -3.5530905723571777,
                                "y": -3.4224905967712402,
                                "r": 3.2664343002773406,
                                "c": 24082
                            },
                            {
                                "x": 3.164159059524536,
                                "y": -4.929034233093262,
                                "r": 3.2245708717487447,
                                "c": 21848
                            },
                            {
                                "x": -3.360358715057373,
                                "y": -1.883870244026184,
                                "r": 3.223502735926842,
                                "c": 21791
                            },
                            {
                                "x": 1.9128974676132202,
                                "y": -1.8609020709991455,
                                "r": 3.2013529720410765,
                                "c": 20609
                            },
                            {
                                "x": -2.0641181468963623,
                                "y": -3.4442238807678223,
                                "r": 3.1905029607975415,
                                "c": 20030
                            },
                            {
                                "x": 10.241869926452637,
                                "y": -0.9167566299438477,
                                "r": 3.1823326587212355,
                                "c": 19594
                            },
                            {
                                "x": 0.5488482117652893,
                                "y": -3.9842538833618164,
                                "r": 3.180158908627539,
                                "c": 19478
                            },
                            {
                                "x": -4.19766902923584,
                                "y": 3.1765944957733154,
                                "r": 3.176036279139495,
                                "c": 19258
                            },
                            {
                                "x": -2.3333687782287598,
                                "y": 0.9562304019927979,
                                "r": 3.1706393823551458,
                                "c": 18970
                            },
                            {
                                "x": 0.009630203247070312,
                                "y": -2.550790548324585,
                                "r": 3.164511655797916,
                                "c": 18643
                            },
                            {
                                "x": 1.7518110275268555,
                                "y": 4.80190372467041,
                                "r": 3.1635746945506336,
                                "c": 18593
                            },
                            {
                                "x": -0.28572481870651245,
                                "y": -2.134328842163086,
                                "r": 3.1631249531519376,
                                "c": 18569
                            },
                            {
                                "x": -3.621951103210449,
                                "y": -4.170267581939697,
                                "r": 3.1582340154411215,
                                "c": 18308
                            },
                            {
                                "x": 2.0393142700195312,
                                "y": -0.14611685276031494,
                                "r": 3.156116483022262,
                                "c": 18195
                            },
                            {
                                "x": -3.1167335510253906,
                                "y": -2.933321475982666,
                                "r": 3.1501011918147066,
                                "c": 17874
                            },
                            {
                                "x": 7.306593894958496,
                                "y": 0.7861315011978149,
                                "r": 3.138651525372911,
                                "c": 17263
                            },
                            {
                                "x": 6.223394393920898,
                                "y": 3.0023584365844727,
                                "r": 3.1383704369987258,
                                "c": 17248
                            },
                            {
                                "x": -1.5974851846694946,
                                "y": 1.2929425239562988,
                                "r": 3.1309684431451914,
                                "c": 16853
                            },
                            {
                                "x": 1.2483406066894531,
                                "y": -0.6993377804756165,
                                "r": 3.1282512555280713,
                                "c": 16708
                            },
                            {
                                "x": -3.013249158859253,
                                "y": -3.2064433097839355,
                                "r": 3.120324563376059,
                                "c": 16285
                            },
                            {
                                "x": -1.8617533445358276,
                                "y": 2.998936891555786,
                                "r": 3.1180383779326886,
                                "c": 16163
                            },
                            {
                                "x": 3.662865400314331,
                                "y": -1.9902251958847046,
                                "r": 3.1157147140394272,
                                "c": 16039
                            },
                            {
                                "x": -5.502094745635986,
                                "y": -0.09235408902168274,
                                "r": 3.1145716213177423,
                                "c": 15978
                            },
                            {
                                "x": -3.906249761581421,
                                "y": -4.289445877075195,
                                "r": 3.1111423431526872,
                                "c": 15795
                            },
                            {
                                "x": -2.5858728885650635,
                                "y": -6.3902201652526855,
                                "r": 3.111048647027959,
                                "c": 15790
                            },
                            {
                                "x": 3.443246841430664,
                                "y": -5.268144607543945,
                                "r": 3.109024810733828,
                                "c": 15682
                            },
                            {
                                "x": -6.49444580078125,
                                "y": 3.4453999996185303,
                                "r": 3.096488269245184,
                                "c": 15013
                            },
                            {
                                "x": 7.619561195373535,
                                "y": 5.484368324279785,
                                "r": 3.0950078704744772,
                                "c": 14934
                            },
                            {
                                "x": 7.196137428283691,
                                "y": 0.46225112676620483,
                                "r": 3.094857956674912,
                                "c": 14926
                            },
                            {
                                "x": 7.684354782104492,
                                "y": -0.32659751176834106,
                                "r": 3.0826587212352896,
                                "c": 14275
                            },
                            {
                                "x": -1.0605719089508057,
                                "y": 3.778937816619873,
                                "r": 3.075181770481973,
                                "c": 13876
                            },
                            {
                                "x": -3.095194101333618,
                                "y": 1.5125765800476074,
                                "r": 3.07325163031257,
                                "c": 13773
                            },
                            {
                                "x": 6.7487287521362305,
                                "y": 0.27548569440841675,
                                "r": 3.0728018889138746,
                                "c": 13749
                            },
                            {
                                "x": -4.509329319000244,
                                "y": 2.771434783935547,
                                "r": 3.0719773630162654,
                                "c": 13705
                            },
                            {
                                "x": 0.018812313675880432,
                                "y": 1.55815589427948,
                                "r": 3.0688666516752865,
                                "c": 13539
                            },
                            {
                                "x": 1.8444002866744995,
                                "y": 0.16577279567718506,
                                "r": 3.059796866801589,
                                "c": 13055
                            },
                            {
                                "x": 1.8641376495361328,
                                "y": -2.2233171463012695,
                                "r": 3.0561801963870776,
                                "c": 12862
                            },
                            {
                                "x": -1.0269432067871094,
                                "y": -1.6211163997650146,
                                "r": 3.054999625215501,
                                "c": 12799
                            },
                            {
                                "x": 5.496940612792969,
                                "y": 5.3389434814453125,
                                "r": 3.049996252155011,
                                "c": 12532
                            },
                            {
                                "x": 13.259990692138672,
                                "y": -3.3264989852905273,
                                "r": 3.0431939134997377,
                                "c": 12169
                            },
                            {
                                "x": 0.43665051460266113,
                                "y": 4.1906633377075195,
                                "r": 3.0367101416685407,
                                "c": 11823
                            },
                            {
                                "x": -1.5182387828826904,
                                "y": -0.6264938116073608,
                                "r": 3.028933363316093,
                                "c": 11408
                            },
                            {
                                "x": -3.473527431488037,
                                "y": -1.4127321243286133,
                                "r": 3.027790270594408,
                                "c": 11347
                            },
                            {
                                "x": 2.3361425399780273,
                                "y": -3.9846553802490234,
                                "r": 3.021531369462559,
                                "c": 11013
                            },
                            {
                                "x": -4.049435615539551,
                                "y": -1.1016592979431152,
                                "r": 3.0210816280638633,
                                "c": 10989
                            },
                            {
                                "x": -4.232792377471924,
                                "y": -6.735654830932617,
                                "r": 3.0192639232441345,
                                "c": 10892
                            },
                            {
                                "x": 5.414191722869873,
                                "y": -0.848857045173645,
                                "r": 3.0120118431901655,
                                "c": 10505
                            },
                            {
                                "x": -4.822662353515625,
                                "y": -6.447019577026367,
                                "r": 3.0083014766509257,
                                "c": 10307
                            },
                            {
                                "x": -5.146997451782227,
                                "y": 4.082787036895752,
                                "r": 3.0061839442320664,
                                "c": 10194
                            },
                            {
                                "x": 4.625715255737305,
                                "y": 5.938154220581055,
                                "r": 3.004741023911251,
                                "c": 10117
                            },
                            {
                                "x": 0.5522027015686035,
                                "y": -2.4665937423706055,
                                "r": 3.0026422307173375,
                                "c": 10005
                            },
                            {
                                "x": -2.2912991046905518,
                                "y": -5.727817535400391,
                                "r": 3.000093696124728,
                                "c": 9869
                            },
                            {
                                "x": 3.3982245922088623,
                                "y": 3.4816904067993164,
                                "r": 3.0,
                                "c": 9864
                            }
                        ]
                    },
                    {
                        "label": "形容詞",
                        "backgroundColor": "#031B88",
                        "data": [
                            {
                                "x": -5.517714500427246,
                                "y": 0.791634738445282,
                                "r": 3.449085525822652,
                                "c": 33829
                            },
                            {
                                "x": 2.7887632846832275,
                                "y": -3.7687058448791504,
                                "r": 3.2557154636084253,
                                "c": 23510
                            },
                            {
                                "x": -6.05691385269165,
                                "y": 3.180593252182007,
                                "r": 3.1089311146090997,
                                "c": 15677
                            },
                            {
                                "x": -4.086882591247559,
                                "y": 0.29298198223114014,
                                "r": 3.0507458211528373,
                                "c": 12572
                            },
                            {
                                "x": -5.264707565307617,
                                "y": 0.3429381251335144,
                                "r": 3.0465294955400646,
                                "c": 12347
                            },
                            {
                                "x": -4.446868896484375,
                                "y": 3.5522735118865967,
                                "r": 3.0438497863728355,
                                "c": 12204
                            },
                            {
                                "x": 1.9014067649841309,
                                "y": -6.741481781005859,
                                "r": 3.0393711116108237,
                                "c": 11965
                            },
                            {
                                "x": -1.6637338399887085,
                                "y": -0.8654773235321045,
                                "r": 3.037347275316693,
                                "c": 11857
                            },
                            {
                                "x": -1.9424347877502441,
                                "y": 3.779240846633911,
                                "r": 3.029102016340604,
                                "c": 11417
                            },
                            {
                                "x": -5.682192325592041,
                                "y": 3.3933372497558594,
                                "r": 3.0221497638857655,
                                "c": 11046
                            }
                        ]
                    }
                ]
            },
            "options": {
                "title": {
                    "display": false
                },
                "tooltips": {
                    "callbacks": {
                        "title": [],
                        "afterLabel": []
                    }
                }
            },
            "tooltips": {
                "title": [
                    [
                        "思う（動詞：*）",
                        "できる（動詞：*）",
                        "言う（動詞：*）",
                        "つく（動詞：*）",
                        "願う（動詞：*）",
                        "出る（動詞：*）",
                        "見る（動詞：*）",
                        "やる（動詞：*）",
                        "受ける（動詞：*）",
                        "行く（動詞：*）",
                        "いただく（動詞：*）",
                        "考える（動詞：*）",
                        "いたす（動詞：*）",
                        "くださる（動詞：*）",
                        "致す（動詞：*）",
                        "頂く（動詞：*）",
                        "出来る（動詞：*）",
                        "行う（動詞：*）",
                        "出す（動詞：*）",
                        "来る（動詞：*）"
                    ],
                    [
                        "コロナウイルス（未定義語：カタカナ）",
                        "コロナウィルス（未定義語：カタカナ）"
                    ],
                    [
                        "コロナ（名詞：普通名詞）",
                        "新型（名詞：普通名詞）",
                        "感染（名詞：サ変名詞）",
                        "人（名詞：普通名詞）",
                        "ウイルス（名詞：普通名詞）",
                        "日本（名詞：地名）",
                        "対策（名詞：普通名詞）",
                        "拡大（名詞：サ変名詞）",
                        "影響（名詞：サ変名詞）",
                        "今（名詞：時相名詞）",
                        "症（名詞：普通名詞）",
                        "検査（名詞：サ変名詞）",
                        "自粛（名詞：サ変名詞）",
                        "医療（名詞：普通名詞）",
                        "事（名詞：普通名詞）",
                        "国（名詞：普通名詞）",
                        "確認（名詞：サ変名詞）",
                        "世界（名詞：普通名詞）",
                        "事態（名詞：普通名詞）",
                        "政府（名詞：普通名詞）",
                        "防止（名詞：サ変名詞）",
                        "東京（名詞：地名）",
                        "私（名詞：普通名詞）",
                        "マスク（名詞：普通名詞）",
                        "情報（名詞：普通名詞）",
                        "店（名詞：普通名詞）",
                        "対応（名詞：サ変名詞）",
                        "中国（名詞：地名）",
                        "状況（名詞：普通名詞）",
                        "経済（名詞：普通名詞）",
                        "中止（名詞：サ変名詞）",
                        "休業（名詞：サ変名詞）",
                        "金（名詞：普通名詞）",
                        "支援（名詞：サ変名詞）",
                        "ニュース（名詞：普通名詞）",
                        "今日（名詞：時相名詞）",
                        "宣言（名詞：サ変名詞）",
                        "国民（名詞：普通名詞）",
                        "病院（名詞：普通名詞）",
                        "患者（名詞：普通名詞）",
                        "発表（名詞：サ変名詞）",
                        "自分（名詞：普通名詞）",
                        "営業（名詞：サ変名詞）",
                        "予定（名詞：サ変名詞）",
                        "開催（名詞：サ変名詞）",
                        "方（名詞：普通名詞）",
                        "生活（名詞：サ変名詞）",
                        "延期（名詞：サ変名詞）",
                        "気（名詞：普通名詞）",
                        "外出（名詞：サ変名詞）",
                        "日（名詞：地名）",
                        "会（名詞：普通名詞）",
                        "所（名詞：普通名詞）",
                        "皆様（名詞：普通名詞）",
                        "知らせ（名詞：普通名詞）",
                        "時間（名詞：時相名詞）",
                        "関係（名詞：サ変名詞）",
                        "危機（名詞：普通名詞）",
                        "県（名詞：普通名詞）",
                        "問題（名詞：普通名詞）",
                        "死亡（名詞：サ変名詞）",
                        "本日（名詞：時相名詞）",
                        "死者（名詞：普通名詞）",
                        "仕事（名詞：サ変名詞）",
                        "客（名詞：普通名詞）",
                        "大阪（名詞：地名）",
                        "米（名詞：地名）",
                        "協力（名詞：サ変名詞）"
                    ],
                    [
                        "ない（形容詞：*）",
                        "緊急だ（形容詞：*）",
                        "いい（形容詞：*）",
                        "必要だ（形容詞：*）",
                        "多い（形容詞：*）",
                        "本当だ（形容詞：*）",
                        "新ただ（形容詞：*）",
                        "可能だ（形容詞：*）",
                        "早い（形容詞：*）",
                        "良い（形容詞：*）"
                    ]
                ],
                "afterLabel": [
                    [
                        "本当だ（形容詞）：0.75<br>今（名詞）：0.72<br>良い（形容詞）：0.7<br>しれる（動詞）：0.69<br>いい（形容詞）：0.68",
                        "出来る（動詞）：0.64<br>必要だ（形容詞）：0.6<br>今（名詞）：0.58<br>考える（動詞）：0.52<br>いい（形容詞）：0.47",
                        "いい（形容詞）：0.71<br>悪い（形容詞）：0.7<br>同じだ（形容詞）：0.69<br>やる（動詞）：0.68<br>誰（名詞）：0.65",
                        "関する（動詞）：0.75<br>症（名詞）：0.53<br>知らせる（動詞）：0.53<br>実施（名詞）：0.51<br>現在（名詞）：0.49",
                        "下さる（動詞）：0.56<br>願い（名詞）：0.52<br>申し上げる（動詞）：0.51<br>くださる（動詞）：0.51<br>皆様（名詞）：0.5",
                        "入る（動詞）：0.54<br>言う（動詞）：0.47<br>多い（形容詞）：0.47<br>怖い（形容詞）：0.46<br>出す（動詞）：0.44",
                        "思う（動詞）：0.6<br>よい（形容詞）：0.58<br>良い（形容詞）：0.56<br>知る（動詞）：0.55<br>いい（形容詞）：0.51",
                        "いい（形容詞）：0.7<br>言う（動詞）：0.68<br>今（名詞）：0.63<br>無い（形容詞）：0.61<br>ない（形容詞）：0.57",
                        "伴う（動詞）：0.71<br>防止（名詞）：0.45<br>知らせ（名詞）：0.45<br>対象（名詞）：0.43<br>新型（名詞）：0.42",
                        "来る（動詞）：0.71<br>いい（形容詞）：0.65<br>家（名詞）：0.56<br>私（名詞）：0.56<br>怖い（形容詞）：0.56",
                        "いたす（動詞）：0.81<br>頂く（動詞）：0.77<br>致す（動詞）：0.7<br>予定（名詞）：0.53<br>くださる（動詞）：0.53",
                        "思う（動詞）：0.67<br>自分（名詞）：0.63<br>今（名詞）：0.62<br>しれる（動詞）：0.57<br>何（名詞）：0.55",
                        "致す（動詞）：0.82<br>いただく（動詞）：0.81<br>申し上げる（動詞）：0.71<br>頂く（動詞）：0.6<br>詳細だ（形容詞）：0.54",
                        "下さる（動詞）：0.87<br>いただく（動詞）：0.53<br>詳細だ（形容詞）：0.51<br>願う（動詞）：0.51<br>いたす（動詞）：0.48",
                        "いたす（動詞）：0.82<br>頂く（動詞）：0.8<br>申し上げる（動詞）：0.72<br>いただく（動詞）：0.7<br>下さる（動詞）：0.52",
                        "致す（動詞）：0.8<br>いただく（動詞）：0.77<br>いたす（動詞）：0.6<br>下さる（動詞）：0.53<br>皆様（名詞）：0.52",
                        "事（名詞）：0.72<br>できる（動詞）：0.64<br>無い（形容詞）：0.59<br>今（名詞）：0.58<br>良い（形容詞）：0.57",
                        "実施（名詞）：0.73<br>開始（名詞）：0.47<br>つく（動詞）：0.43<br>求める（動詞）：0.41<br>本日（名詞）：0.39",
                        "言う（動詞）：0.55<br>無い（形容詞）：0.48<br>政府（名詞）：0.45<br>ない（形容詞）：0.45<br>出る（動詞）：0.44",
                        "行く（動詞）：0.71<br>本当だ（形容詞）：0.51<br>落ち着く（動詞）：0.5<br>欲しい（形容詞）：0.49<br>私（名詞）：0.47"
                    ],
                    [
                        "コロナウィルス（未定義語）：0.86<br>ウイルス（名詞）：0.65<br>感染（名詞）：0.5<br>症（名詞）：0.49<br>伴う（動詞）：0.42",
                        "コロナウイルス（未定義語）：0.86<br>ウイルス（名詞）：0.61<br>コロナ（名詞）：0.4<br>知らせ（名詞）：0.4<br>伴う（動詞）：0.39"
                    ],
                    [
                        "コロナウィルス（未定義語）：0.4<br>コロナウイルス（未定義語）：0.34<br>ない（形容詞）：0.23<br>状態（名詞）：0.23<br>減る（動詞）：0.21",
                        "症（名詞）：0.57<br>感染（名詞）：0.55<br>伴う（動詞）：0.52<br>知らせ（名詞）：0.49<br>発表（名詞）：0.47",
                        "新型（名詞）：0.55<br>コロナウイルス（未定義語）：0.5<br>知らせ（名詞）：0.44<br>伴う（動詞）：0.43<br>現在（名詞）：0.43",
                        "自分（名詞）：0.66<br>しれる（動詞）：0.61<br>死ぬ（動詞）：0.61<br>誰（名詞）：0.58<br>多い（形容詞）：0.58",
                        "コロナウイルス（未定義語）：0.65<br>コロナウィルス（未定義語）：0.61<br>ウィルス（名詞）：0.42<br>感染（名詞）：0.35<br>発表（名詞）：0.31",
                        "韓国（名詞）：0.67<br>国（名詞）：0.65<br>アメリカ（名詞）：0.61<br>世界（名詞）：0.61<br>米国（名詞）：0.57",
                        "対応（名詞）：0.53<br>会議（名詞）：0.45<br>対する（動詞）：0.41<br>議員（名詞）：0.41<br>政府（名詞）：0.37",
                        "知らせ（名詞）：0.54<br>症（名詞）：0.48<br>臨時（名詞）：0.48<br>伴う（動詞）：0.44<br>新型（名詞）：0.39",
                        "イベント（名詞）：0.47<br>状況（名詞）：0.36<br>予定（名詞）：0.34<br>販売（名詞）：0.33<br>頂く（動詞）：0.33",
                        "思う（動詞）：0.72<br>本当だ（形容詞）：0.65<br>私（名詞）：0.64<br>自分（名詞）：0.64<br>やる（動詞）：0.63",
                        "新型（名詞）：0.57<br>知らせ（名詞）：0.53<br>つく（動詞）：0.53<br>コロナウイルス（未定義語）：0.49<br>伴う（動詞）：0.48",
                        "ｐｃｒ（未定義語）：0.82<br>陽性だ（形容詞）：0.69<br>症状（名詞）：0.53<br>入院（名詞）：0.49<br>肺炎（名詞）：0.49",
                        "休業（名詞）：0.48<br>外出（名詞）：0.46<br>制限（名詞）：0.45<br>要請（名詞）：0.39<br>急だ（形容詞）：0.34",
                        "病院（名詞）：0.5<br>患者（名詞）：0.43<br>医師（名詞）：0.42<br>治療（名詞）：0.4<br>現場（名詞）：0.36",
                        "出来る（動詞）：0.72<br>無い（形容詞）：0.64<br>思う（動詞）：0.64<br>自分（名詞）：0.58<br>言う（動詞）：0.58",
                        "政府（名詞）：0.67<br>日本（名詞）：0.65<br>国民（名詞）：0.55<br>中国（名詞）：0.51<br>韓国（名詞）：0.51",
                        "発表（名詞）：0.62<br>新ただ（形容詞）：0.61<br>例（名詞）：0.6<br>男性（名詞）：0.56<br>市（名詞）：0.52",
                        "米国（名詞）：0.63<br>日本（名詞）：0.61<br>中国（名詞）：0.6<br>アメリカ（名詞）：0.59<br>ｗｈｏ（名詞）：0.58",
                        "延長（名詞）：0.32<br>政府（名詞）：0.29<br>出す（動詞）：0.28<br>要請（名詞）：0.28<br>伴う（動詞）：0.28",
                        "国（名詞）：0.67<br>国民（名詞）：0.61<br>対する（動詞）：0.56<br>政権（名詞）：0.53<br>経済（名詞）：0.52",
                        "伴う（動詞）：0.7<br>予防（名詞）：0.6<br>知らせ（名詞）：0.54<br>臨時（名詞）：0.49<br>知らせる（動詞）：0.47",
                        "都（名詞）：0.79<br>大阪（名詞）：0.61<br>速報（名詞）：0.51<br>新ただ（形容詞）：0.44<br>全国（名詞）：0.4",
                        "今（名詞）：0.64<br>自分（名詞）：0.64<br>本当だ（形容詞）：0.64<br>思う（動詞）：0.63<br>いい（形容詞）：0.59",
                        "使う（動詞）：0.4<br>作る（動詞）：0.37<br>入る（動詞）：0.32<br>気（名詞）：0.29<br>販売（名詞）：0.28",
                        "関連（名詞）：0.59<br>サイト（名詞）：0.57<br>更新（名詞）：0.47<br>関する（動詞）：0.43<br>発生（名詞）：0.4",
                        "店舗（名詞）：0.7<br>飲食（名詞）：0.63<br>営業（名詞）：0.55<br>客（名詞）：0.5<br>休業（名詞）：0.48",
                        "対策（名詞）：0.53<br>対する（動詞）：0.5<br>政府（名詞）：0.41<br>つく（動詞）：0.37<br>関する（動詞）：0.36",
                        "米国（名詞）：0.71<br>武漢（名詞）：0.71<br>米（名詞）：0.7<br>ｗｈｏ（名詞）：0.67<br>アメリカ（名詞）：0.65",
                        "今後（名詞）：0.48<br>つく（動詞）：0.45<br>現在（名詞）：0.43<br>知らせる（動詞）：0.42<br>時期（名詞）：0.42",
                        "社会（名詞）：0.53<br>政府（名詞）：0.52<br>国（名詞）：0.48<br>企業（名詞）：0.48<br>日本（名詞）：0.47",
                        "延期（名詞）：0.88<br>開催（名詞）：0.8<br>予定（名詞）：0.71<br>公演（名詞）：0.7<br>イベント（名詞）：0.64",
                        "営業（名詞）：0.66<br>店舗（名詞）：0.57<br>臨時（名詞）：0.51<br>自粛（名詞）：0.48<br>店（名詞）：0.48",
                        "給付（名詞）：0.67<br>事業（名詞）：0.59<br>補償（名詞）：0.51<br>支援（名詞）：0.51<br>企業（名詞）：0.47",
                        "事業（名詞）：0.68<br>給付（名詞）：0.55<br>企業（名詞）：0.52<br>金（名詞）：0.51<br>応援（名詞）：0.47",
                        "テレビ（名詞）：0.48<br>報道（名詞）：0.45<br>ｎｈｋ（未定義語）：0.4<br>記事（名詞）：0.38<br>速報（名詞）：0.36",
                        "元気だ（形容詞）：0.64<br>昨日（名詞）：0.63<br>日（名詞）：0.6<br>頑張る（動詞）：0.57<br>毎日（名詞）：0.55",
                        "要請（名詞）：0.37<br>伴う（動詞）：0.31<br>拡大（名詞）：0.29<br>延長（名詞）：0.29<br>休業（名詞）：0.29",
                        "政治（名詞）：0.65<br>政権（名詞）：0.64<br>安倍（名詞）：0.63<br>政府（名詞）：0.61<br>安倍（名詞）：0.61",
                        "患者（名詞）：0.71<br>入院（名詞）：0.68<br>医師（名詞）：0.59<br>重症（名詞）：0.51<br>職員（名詞）：0.51",
                        "病院（名詞）：0.71<br>入院（名詞）：0.69<br>重症（名詞）：0.62<br>陽性だ（形容詞）：0.58<br>例（名詞）：0.56",
                        "確認（名詞）：0.62<br>速報（名詞）：0.6<br>新ただ（形容詞）：0.59<br>実施（名詞）：0.52<br>市（名詞）：0.51",
                        "誰（名詞）：0.77<br>しれる（動詞）：0.69<br>大切だ（形容詞）：0.69<br>思う（動詞）：0.68<br>人（名詞）：0.66",
                        "店舗（名詞）：0.68<br>休業（名詞）：0.66<br>変更（名詞）：0.61<br>臨時（名詞）：0.57<br>店（名詞）：0.55",
                        "延期（名詞）：0.73<br>中止（名詞）：0.71<br>イベント（名詞）：0.67<br>公演（名詞）：0.65<br>知らせる（動詞）：0.65",
                        "中止（名詞）：0.8<br>延期（名詞）：0.76<br>公演（名詞）：0.73<br>イベント（名詞）：0.71<br>予定（名詞）：0.62",
                        "ｒｔ（未定義語）：0.43<br>下さる（動詞）：0.41<br>皆さん（名詞）：0.41<br>相談（名詞）：0.39<br>くださる（動詞）：0.37",
                        "仕事（名詞）：0.53<br>給付（名詞）：0.52<br>社会（名詞）：0.48<br>補償（名詞）：0.46<br>必要だ（形容詞）：0.45",
                        "中止（名詞）：0.88<br>開催（名詞）：0.76<br>公演（名詞）：0.74<br>予定（名詞）：0.73<br>決定（名詞）：0.65",
                        "思う（動詞）：0.47<br>良い（形容詞）：0.45<br>今日（名詞）：0.45<br>いい（形容詞）：0.42<br>つける（動詞）：0.41",
                        "自粛（名詞）：0.46<br>要請（名詞）：0.4<br>家（名詞）：0.39<br>行動（名詞）：0.36<br>急だ（形容詞）：0.35",
                        "おく（動詞）：0.55<br>ロナ（名詞）：0.55<br>け（名詞）：0.5<br>うむ（動詞）：0.49<br>画す（動詞）：0.48",
                        "会議（名詞）：0.58<br>開催（名詞）：0.46<br>全国（名詞）：0.45<br>オンライン（名詞）：0.45<br>イベント（名詞）：0.38",
                        "職員（名詞）：0.42<br>機関（名詞）：0.38<br>保健（名詞）：0.36<br>市（名詞）：0.34<br>電話（名詞）：0.34",
                        "皆さん（名詞）：0.6<br>申し上げる（動詞）：0.53<br>頂く（動詞）：0.52<br>致す（動詞）：0.51<br>願う（動詞）：0.5",
                        "知らせる（動詞）：0.78<br>伴う（動詞）：0.68<br>予定（名詞）：0.6<br>防止（名詞）：0.54<br>公演（名詞）：0.54",
                        "変更（名詞）：0.49<br>営業（名詞）：0.4<br>店舗（名詞）：0.4<br>期間（名詞）：0.34<br>家（名詞）：0.33",
                        "従事（名詞）：0.6<br>機関（名詞）：0.51<br>現場（名詞）：0.45<br>崩壊（名詞）：0.36<br>感謝（名詞）：0.35",
                        "政治（名詞）：0.5<br>日本（名詞）：0.42<br>政権（名詞）：0.4<br>感（名詞）：0.39<br>社会（名詞）：0.39",
                        "市（名詞）：0.67<br>例（名詞）：0.51<br>確認（名詞）：0.5<br>新ただ（形容詞）：0.47<br>発表（名詞）：0.45",
                        "政治（名詞）：0.59<br>社会（名詞）：0.51<br>政権（名詞）：0.48<br>責任（名詞）：0.47<br>今回（名詞）：0.46",
                        "死者（名詞）：0.75<br>肺炎（名詞）：0.61<br>重症（名詞）：0.61<br>少ない（形容詞）：0.58<br>亡くなる（動詞）：0.57",
                        "知らせる（動詞）：0.56<br>現在（名詞）：0.51<br>昨日（名詞）：0.45<br>実施（名詞）：0.44<br>更新（名詞）：0.44",
                        "死亡（名詞）：0.75<br>少ない（形容詞）：0.62<br>米国（名詞）：0.5<br>アメリカ（名詞）：0.48<br>亡くなる（動詞）：0.45",
                        "働く（動詞）：0.68<br>家（名詞）：0.66<br>減る（動詞）：0.65<br>私（名詞）：0.59<br>行く（動詞）：0.55",
                        "営業（名詞）：0.54<br>店（名詞）：0.5<br>店舗（名詞）：0.48<br>頂く（動詞）：0.47<br>皆様（名詞）：0.47",
                        "都（名詞）：0.63<br>東京（名詞）：0.61<br>知事（名詞）：0.51<br>市民（名詞）：0.36<br>病院（名詞）：0.35",
                        "米国（名詞）：0.85<br>中国（名詞）：0.7<br>アメリカ（名詞）：0.7<br>ｗｈｏ（名詞）：0.55<br>武漢（名詞）：0.51",
                        "願う（動詞）：0.48<br>申し上げる（動詞）：0.48<br>願い（名詞）：0.47<br>いたす（動詞）：0.45<br>支援（名詞）：0.42"
                    ],
                    [
                        "無い（形容詞）：0.77<br>言う（動詞）：0.61<br>人間（名詞）：0.59<br>いい（形容詞）：0.58<br>やる（動詞）：0.57",
                        "伴う（動詞）：0.38<br>全国（名詞）：0.37<br>延長（名詞）：0.36<br>受ける（動詞）：0.34<br>政府（名詞）：0.33",
                        "言う（動詞）：0.71<br>良い（形容詞）：0.71<br>やる（動詞）：0.7<br>よい（形容詞）：0.68<br>思う（動詞）：0.68",
                        "できる（動詞）：0.6<br>ない（形容詞）：0.54<br>求める（動詞）：0.46<br>生活（名詞）：0.45<br>国民（名詞）：0.43",
                        "少ない（形容詞）：0.65<br>増える（動詞）：0.64<br>人（名詞）：0.58<br>減る（動詞）：0.52<br>同じだ（形容詞）：0.52",
                        "思う（動詞）：0.75<br>今（名詞）：0.65<br>気持ち（名詞）：0.65<br>私（名詞）：0.64<br>良い（形容詞）：0.61",
                        "速報（名詞）：0.67<br>確認（名詞）：0.61<br>発表（名詞）：0.59<br>男性（名詞）：0.54<br>例（名詞）：0.53",
                        "リスク（名詞）：0.52<br>高い（形容詞）：0.48<br>症状（名詞）：0.41<br>重症（名詞）：0.38<br>しれる（動詞）：0.38",
                        "終息（名詞）：0.6<br>収束（名詞）：0.55<br>日（名詞）：0.49<br>待つ（動詞）：0.48<br>頑張る（動詞）：0.48",
                        "悪い（形容詞）：0.71<br>いい（形容詞）：0.71<br>思う（動詞）：0.7<br>よい（形容詞）：0.63<br>欲しい（形容詞）：0.62"
                    ]
                ]
            }
        },
        "wc": "2020-03-29_2020-05-22_cv19m.png"
    },
    "entities": {
        "trend": [
            "<blockquote class=\"twitter-tweet\"><p lang=\"ja\" dir=\"ltr\">【緊急企画】<br>新型コロナウイルス感染拡大防止の為に、現場の最前線で命懸けで闘う医療従事者の方々に何かできることはないかと寄付企画を立ち上げました。<br><br>本ツイートのRT数に応じて、当社から寄付をします。<br>医療従事者の方々への応援メッセージとともにRTをぜひお願いします！<a href=\"https://twitter.com/hashtag/%E3%82%B3%E3%83%AD%E3%83%8A%E3%81%AB%E8%B2%A0%E3%81%91%E3%82%8B%E3%81%AA?src=hash&amp;ref_src=twsrc%5Etfw\">#コロナに負けるな</a> <a href=\"https://t.co/kgrxDDwS4r\">pic.twitter.com/kgrxDDwS4r</a></p>&mdash; クオカード(公式) (@quocardofficial) <a href=\"https://twitter.com/quocardofficial/status/1250982321848823810?ref_src=twsrc%5Etfw\">April 17, 2020</a></blockquote>\n<script async src=\"https://platform.twitter.com/widgets.js\" charset=\"utf-8\"></script>\n",
            "<blockquote class=\"twitter-tweet\"><p lang=\"ja\" dir=\"ltr\">【速報 JUST IN 】コメディアンの志村けんさん死去 新型コロナ感染で肺炎発症 <a href=\"https://twitter.com/hashtag/nhk_news?src=hash&amp;ref_src=twsrc%5Etfw\">#nhk_news</a> <a href=\"https://t.co/SkK4h89YvD\">https://t.co/SkK4h89YvD</a></p>&mdash; NHKニュース (@nhk_news) <a href=\"https://twitter.com/nhk_news/status/1244426374707732480?ref_src=twsrc%5Etfw\">March 30, 2020</a></blockquote>\n<script async src=\"https://platform.twitter.com/widgets.js\" charset=\"utf-8\"></script>\n",
            "<blockquote class=\"twitter-tweet\"><p lang=\"ja\" dir=\"ltr\">【 <a href=\"https://twitter.com/hashtag/%E5%89%8D%E6%BE%A4%E3%81%B2%E3%81%A8%E3%82%8A%E8%A6%AA%E5%BF%9C%E6%8F%B4%E5%9F%BA%E9%87%91?src=hash&amp;ref_src=twsrc%5Etfw\">#前澤ひとり親応援基金</a> 創設】<br><br>第一弾は、現金10万円を1万人のシングルマザー＆ファザーに配ります。<br><br>コロナでひとり親の皆さまは本当に大変。僕なりにできることします。<br><br>応募はフォロー＆RTの上、下記アンケートにお答えください。5/15締切で、5/18入金開始です。<a href=\"https://t.co/E56XcrilZQ\">https://t.co/E56XcrilZQ</a></p>&mdash; Yusaku Maezawa (MZ) 前澤 友作 (@yousuck2020) <a href=\"https://twitter.com/yousuck2020/status/1259415636108701696?ref_src=twsrc%5Etfw\">May 10, 2020</a></blockquote>\n<script async src=\"https://platform.twitter.com/widgets.js\" charset=\"utf-8\"></script>\n",
            "<blockquote class=\"twitter-tweet\"><p lang=\"ja\" dir=\"ltr\">【訃報】コメディアンの志村けんさん死去 70歳<a href=\"https://t.co/Th6NiGxbxR\">https://t.co/Th6NiGxbxR</a><br><br>新型コロナウイルスに感染して肺炎を発症し、入院して治療を受けていたコメディアンの志村けんさんが、29日夜、東京都内の病院で亡くなりました。</p>&mdash; ライブドアニュース (@livedoornews) <a href=\"https://twitter.com/livedoornews/status/1244427261756862464?ref_src=twsrc%5Etfw\">March 30, 2020</a></blockquote>\n<script async src=\"https://platform.twitter.com/widgets.js\" charset=\"utf-8\"></script>\n",
            "<blockquote class=\"twitter-tweet\"><p lang=\"ja\" dir=\"ltr\">歴史に刻まれるであろう世界的大流行を起こしている新型コロナウイルス「SARS-CoV-2」。その基本的な特徴・感染のメカニズム・対策など、有益そうなサイエンス情報を図解にまとめてみました。なるべく信頼性の高いと思われる資料を参照しましたが、日々更新される最新情報と合わせつつご活用ください。 <a href=\"https://t.co/Y68oM0eKjL\">pic.twitter.com/Y68oM0eKjL</a></p>&mdash; ぬまがさワタリ@『ふしぎな昆虫大研究』発売中 (@numagasa) <a href=\"https://twitter.com/numagasa/status/1248181205872205825?ref_src=twsrc%5Etfw\">April 9, 2020</a></blockquote>\n<script async src=\"https://platform.twitter.com/widgets.js\" charset=\"utf-8\"></script>\n",
            "<blockquote class=\"twitter-tweet\"><p lang=\"ja\" dir=\"ltr\">【NHKニュース速報 09:48】<br>コメディアンの志村けんさん死去<br>新型コロナウイルスで肺炎発症　７０歳</p>&mdash; 特務機関NERV (@UN_NERV) <a href=\"https://twitter.com/UN_NERV/status/1244426172382887936?ref_src=twsrc%5Etfw\">March 30, 2020</a></blockquote>\n<script async src=\"https://platform.twitter.com/widgets.js\" charset=\"utf-8\"></script>\n",
            "<blockquote class=\"twitter-tweet\"><p lang=\"ja\" dir=\"ltr\">笑いすぎてお腹が痛い。<br>オンライン会議のあとカメラを切り忘れた男性。顔しか映らないからスボン履かずに参加。結果、全員にパンツ姿を見られて大爆笑。ある意味コロナより恐ろしい(笑) <a href=\"https://t.co/euTx0LZimW\">pic.twitter.com/euTx0LZimW</a></p>&mdash; ティエン🇨🇳中国トレンド (@tian_chugokugo) <a href=\"https://twitter.com/tian_chugokugo/status/1248022813052530690?ref_src=twsrc%5Etfw\">April 8, 2020</a></blockquote>\n<script async src=\"https://platform.twitter.com/widgets.js\" charset=\"utf-8\"></script>\n",
            "<blockquote class=\"twitter-tweet\"><p lang=\"ja\" dir=\"ltr\">ヤマト運輸は新型コロナウィルス対策として『宅急便』を非対面🚪📦でお受取りいただく対応を行っております。ご希望されるお客さまは、ぜひご利用ください。<a href=\"https://twitter.com/hashtag/%E3%83%A4%E3%83%9E%E3%83%88%E9%81%8B%E8%BC%B8?src=hash&amp;ref_src=twsrc%5Etfw\">#ヤマト運輸</a> <a href=\"https://twitter.com/hashtag/%E3%82%AF%E3%83%AD%E3%83%8D%E3%82%B3%E3%83%A4%E3%83%9E%E3%83%88?src=hash&amp;ref_src=twsrc%5Etfw\">#クロネコヤマト</a>  <a href=\"https://twitter.com/hashtag/%E5%AE%85%E6%80%A5%E4%BE%BF?src=hash&amp;ref_src=twsrc%5Etfw\">#宅急便</a>  <a href=\"https://twitter.com/hashtag/%E5%AE%85%E9%85%8D?src=hash&amp;ref_src=twsrc%5Etfw\">#宅配</a> <a href=\"https://t.co/b5wiQmrt2n\">pic.twitter.com/b5wiQmrt2n</a></p>&mdash; ヤマトグループ (@yamato_19191129) <a href=\"https://twitter.com/yamato_19191129/status/1245582104664006658?ref_src=twsrc%5Etfw\">April 2, 2020</a></blockquote>\n<script async src=\"https://platform.twitter.com/widgets.js\" charset=\"utf-8\"></script>\n",
            "<blockquote class=\"twitter-tweet\"><p lang=\"ja\" dir=\"ltr\">【拡散希望】本日のヒカキンTVはこちら！→小池都知事にコロナの質問しまくってみた【新型コロナウイルス】 <a href=\"https://t.co/LH9N791Xtg\">https://t.co/LH9N791Xtg</a> <a href=\"https://twitter.com/YouTube?ref_src=twsrc%5Etfw\">@YouTube</a>さんから <a href=\"https://t.co/PyNFvUtJjZ\">pic.twitter.com/PyNFvUtJjZ</a></p>&mdash; HIKAKIN😎ヒカキン 【YouTuber】 (@hikakin) <a href=\"https://twitter.com/hikakin/status/1248525115748274178?ref_src=twsrc%5Etfw\">April 10, 2020</a></blockquote>\n<script async src=\"https://platform.twitter.com/widgets.js\" charset=\"utf-8\"></script>\n",
            "<blockquote class=\"twitter-tweet\"><p lang=\"ja\" dir=\"ltr\">タンクトップの妖精からのお願いです。<br>「コロナ自粛」 <a href=\"https://t.co/uIth39FHBy\">pic.twitter.com/uIth39FHBy</a></p>&mdash; カマたく@CRAZE (@takuya_hyon) <a href=\"https://twitter.com/takuya_hyon/status/1246911366008463360?ref_src=twsrc%5Etfw\">April 5, 2020</a></blockquote>\n<script async src=\"https://platform.twitter.com/widgets.js\" charset=\"utf-8\"></script>\n"
        ],
        "hashtag": [
            {
                "text": "新型コロナウイルス",
                "count": 4266,
                "vertified_count": 2054
            },
            {
                "text": "コロナ",
                "count": 4211,
                "vertified_count": 161
            },
            {
                "text": "nhk_news",
                "count": 3654,
                "vertified_count": 3644
            },
            {
                "text": "新型コロナ",
                "count": 1783,
                "vertified_count": 854
            },
            {
                "text": "新型肺炎",
                "count": 1594,
                "vertified_count": 1401
            },
            {
                "text": "検察庁法改正案に抗議します",
                "count": 1203,
                "vertified_count": 68
            },
            {
                "text": "拡散希望",
                "count": 1064,
                "vertified_count": 2
            },
            {
                "text": "神戸新聞",
                "count": 1013,
                "vertified_count": 979
            },
            {
                "text": "note",
                "count": 952,
                "vertified_count": 97
            },
            {
                "text": "東洋経済オンライン",
                "count": 732,
                "vertified_count": 498
            }
        ],
        "url": [
            {
                "domain": "twitter.com",
                "count": 32646,
                "vertified_count": 2554
            },
            {
                "domain": "www3.nhk.or.jp",
                "count": 12752,
                "vertified_count": 7685
            },
            {
                "domain": "headlines.yahoo.co.jp",
                "count": 8659,
                "vertified_count": 750
            },
            {
                "domain": "h",
                "count": 8048,
                "vertified_count": 2438
            },
            {
                "domain": "youtu.be",
                "count": 6513,
                "vertified_count": 945
            },
            {
                "domain": "bit.ly",
                "count": 5124,
                "vertified_count": 2677
            },
            {
                "domain": "www.jiji.com",
                "count": 4733,
                "vertified_count": 3334
            },
            {
                "domain": "mainichi.jp",
                "count": 4548,
                "vertified_count": 2771
            },
            {
                "domain": "www.asahi.com",
                "count": 4136,
                "vertified_count": 1858
            },
            {
                "domain": "www.nikkei.com",
                "count": 3426,
                "vertified_count": 1372
            }
        ]
    }
}